{
  "schema": "game-drive-run-summary-v1",
  "checkpoint_id": "capability_magic_ball_throw",
  "checkpoint": "work/game_drive_capability_ladder/checkpoints/capability_magic_ball_throw.json",
  "save": "moon-switches-room.LBA",
  "run_dir": "work/game_drive_capability_ladder/runs/capability_magic_ball_throw_20260503T155502Z",
  "verdict": "checkpoint_passed_actions_recorded",
  "pid": 32756,
  "autosave": {
    "hidden": false
  },
  "runtime_before_pose": {
    "active_cube": 31,
    "hero_count": 17,
    "hero_x": 4869,
    "hero_y": 512,
    "hero_z": 8241,
    "hero_beta": 2979,
    "magic_level": 3,
    "magic_point": 60,
    "magic_ball_flag": 1,
    "action_normal": 0,
    "magic_ball_index": 0,
    "magic_ball_type": 0,
    "magic_ball_count": 0,
    "magic_ball_flags": 61,
    "comportement": 1
  },
  "startup": {
    "enter_count": 3
  },
  "pose_result": {
    "method": "direct_pose",
    "before": {
      "module_name": "LBA2.EXE",
      "module_base": "0x400000",
      "hero_base": "0x49a19c",
      "old_x": 4869,
      "old_y": 512,
      "old_z": 8241,
      "x": 4869,
      "y": 512,
      "z": 8241,
      "beta": 2979,
      "old_beta": 6815744,
      "bound_angle": {
        "move_speed": 0,
        "move_acc": 1,
        "move_last_timer": 0,
        "cur": 249561088,
        "end": 96
      },
      "beta_debug": {
        "beta": 2979,
        "degrees": 261.826171875,
        "heading": "W"
      }
    },
    "teleport": {
      "module_name": "LBA2.EXE",
      "module_base": "0x400000",
      "hero_base": "0x49a19c",
      "old_x": 4866,
      "old_y": 512,
      "old_z": 8324,
      "x": 4866,
      "y": 512,
      "z": 8324,
      "beta": 2979,
      "old_beta": 6815744,
      "bound_angle": {
        "move_speed": 0,
        "move_acc": 1,
        "move_last_timer": 0,
        "cur": 249561088,
        "end": 96
      },
      "beta_debug": {
        "beta": 2979,
        "degrees": 261.826171875,
        "heading": "W"
      },
      "target_position": {
        "x": 4866,
        "y": 512,
        "z": 8324
      },
      "sync_old_position": true,
      "sync_candidate_position": true,
      "final_delta_position": {
        "x": 0,
        "y": 0,
        "z": 0
      }
    },
    "heading": {
      "module_name": "LBA2.EXE",
      "module_base": "0x400000",
      "hero_base": "0x49a19c",
      "old_x": 4866,
      "old_y": 512,
      "old_z": 8324,
      "x": 4866,
      "y": 512,
      "z": 8324,
      "beta": 2995,
      "old_beta": 2995,
      "bound_angle": {
        "move_speed": 0,
        "move_acc": 0,
        "move_last_timer": 0,
        "cur": 2995,
        "end": 2995
      },
      "beta_debug": {
        "beta": 2995,
        "degrees": 263.232421875,
        "heading": "W"
      },
      "target_beta": 2995,
      "target_beta_debug": {
        "beta": 2995,
        "degrees": 263.232421875,
        "heading": "W"
      },
      "final_delta_beta": 0,
      "verify_tolerance_beta": 32,
      "verified_within_tolerance": true,
      "sync_bound_angle": true,
      "set_old_beta": true,
      "sustain_ms": 200,
      "interval_ms": 16
    },
    "after": {
      "module_name": "LBA2.EXE",
      "module_base": "0x400000",
      "hero_base": "0x49a19c",
      "old_x": 4866,
      "old_y": 512,
      "old_z": 8324,
      "x": 4866,
      "y": 512,
      "z": 8324,
      "beta": 2995,
      "old_beta": 2995,
      "bound_angle": {
        "move_speed": 0,
        "move_acc": 0,
        "move_last_timer": 0,
        "cur": 2995,
        "end": 2995
      },
      "beta_debug": {
        "beta": 2995,
        "degrees": 263.232421875,
        "heading": "W"
      }
    }
  },
  "runtime_before_visual": {
    "active_cube": 31,
    "hero_count": 17,
    "hero_x": 4866,
    "hero_y": 512,
    "hero_z": 8324,
    "hero_beta": 2995,
    "magic_level": 3,
    "magic_point": 60,
    "magic_ball_flag": 1,
    "action_normal": 0,
    "magic_ball_index": 0,
    "magic_ball_type": 0,
    "magic_ball_count": 0,
    "magic_ball_flags": 61,
    "comportement": 1
  },
  "checkpoint_screenshot": "work/game_drive_capability_ladder/runs/capability_magic_ball_throw_20260503T155502Z/after_pose_set_before_action.png",
  "visual_source": "live_window_capture",
  "visual_result": {
    "checkpoint_id": "capability_magic_ball_throw",
    "matches": true,
    "confidence": "high",
    "summary": "Twinsen is visible standing in the Emerald Moon switch room, the row of three pedestal switches is visible ahead/left of him including the middle switch target, and the view is normal gameplay with no dialog or menu overlay. Twinsen appears upright and controllable, with no unsafe pose signs such as falling, stuck animation, or incapacitation.",
    "derived_mismatches": [],
    "verdict": "visual_checkpoint_matches"
  },
  "actions": [
    {
      "action": "press_1_0_08_sec",
      "before": {
        "active_cube": 31,
        "hero_count": 17,
        "hero_x": 4866,
        "hero_y": 512,
        "hero_z": 8324,
        "hero_beta": 2995,
        "magic_level": 3,
        "magic_point": 60,
        "magic_ball_flag": 1,
        "action_normal": 0,
        "magic_ball_index": 0,
        "magic_ball_type": 0,
        "magic_ball_count": 0,
        "magic_ball_flags": 61,
        "comportement": 1
      },
      "poll": {
        "sample_count": 23,
        "duration_ms": 1464,
        "changed_fields": {},
        "samples": [
          {
            "active_cube": 31,
            "hero_count": 17,
            "hero_x": 4866,
            "hero_y": 512,
            "hero_z": 8324,
            "hero_beta": 2995,
            "magic_level": 3,
            "magic_point": 60,
            "magic_ball_flag": 1,
            "action_normal": 0,
            "magic_ball_index": 0,
            "magic_ball_type": 0,
            "magic_ball_count": 0,
            "magic_ball_flags": 61,
            "comportement": 1,
            "extras": {
              "active_extra_count": 0,
              "sprite_counts": {},
              "active_extras": []
            },
            "dialog": {
              "current_dial": 0,
              "pt_text": "0x0F29044C",
              "pt_dial": "0x00000000",
              "cursor_offset": null
            },
            "_t_ms": 51
          },
          {
            "active_cube": 31,
            "hero_count": 17,
            "hero_x": 4866,
            "hero_y": 512,
            "hero_z": 8324,
            "hero_beta": 2995,
            "magic_level": 3,
            "magic_point": 60,
            "magic_ball_flag": 1,
            "action_normal": 0,
            "magic_ball_index": 0,
            "magic_ball_type": 0,
            "magic_ball_count": 0,
            "magic_ball_flags": 61,
            "comportement": 1,
            "extras": {
              "active_extra_count": 0,
              "sprite_counts": {},
              "active_extras": []
            },
            "dialog": {
              "current_dial": 0,
              "pt_text": "0x0F29044C",
              "pt_dial": "0x00000000",
              "cursor_offset": null
            },
            "_t_ms": 105
          },
          {
            "active_cube": 31,
            "hero_count": 17,
            "hero_x": 4866,
            "hero_y": 512,
            "hero_z": 8324,
            "hero_beta": 2995,
            "magic_level": 3,
            "magic_point": 60,
            "magic_ball_flag": 1,
            "action_normal": 0,
            "magic_ball_index": 0,
            "magic_ball_type": 0,
            "magic_ball_count": 0,
            "magic_ball_flags": 61,
            "comportement": 1,
            "extras": {
              "active_extra_count": 0,
              "sprite_counts": {},
              "active_extras": []
            },
            "dialog": {
              "current_dial": 0,
              "pt_text": "0x0F29044C",
              "pt_dial": "0x00000000",
              "cursor_offset": null
            },
            "_t_ms": 158
          },
          {
            "active_cube": 31,
            "hero_count": 17,
            "hero_x": 4866,
            "hero_y": 512,
            "hero_z": 8324,
            "hero_beta": 2995,
            "magic_level": 3,
            "magic_point": 60,
            "magic_ball_flag": 1,
            "action_normal": 0,
            "magic_ball_index": 0,
            "magic_ball_type": 0,
            "magic_ball_count": 0,
            "magic_ball_flags": 61,
            "comportement": 1,
            "extras": {
              "active_extra_count": 0,
              "sprite_counts": {},
              "active_extras": []
            },
            "dialog": {
              "current_dial": 0,
              "pt_text": "0x0F29044C",
              "pt_dial": "0x00000000",
              "cursor_offset": null
            },
            "_t_ms": 211
          },
          {
            "active_cube": 31,
            "hero_count": 17,
            "hero_x": 4866,
            "hero_y": 512,
            "hero_z": 8324,
            "hero_beta": 2995,
            "magic_level": 3,
            "magic_point": 60,
            "magic_ball_flag": 1,
            "action_normal": 0,
            "magic_ball_index": 0,
            "magic_ball_type": 0,
            "magic_ball_count": 0,
            "magic_ball_flags": 61,
            "comportement": 1,
            "extras": {
              "active_extra_count": 0,
              "sprite_counts": {},
              "active_extras": []
            },
            "dialog": {
              "current_dial": 0,
              "pt_text": "0x0F29044C",
              "pt_dial": "0x00000000",
              "cursor_offset": null
            },
            "_t_ms": 264
          },
          {
            "active_cube": 31,
            "hero_count": 17,
            "hero_x": 4866,
            "hero_y": 512,
            "hero_z": 8324,
            "hero_beta": 2995,
            "magic_level": 3,
            "magic_point": 60,
            "magic_ball_flag": 1,
            "action_normal": 0,
            "magic_ball_index": 0,
            "magic_ball_type": 0,
            "magic_ball_count": 0,
            "magic_ball_flags": 61,
            "comportement": 1,
            "extras": {
              "active_extra_count": 0,
              "sprite_counts": {},
              "active_extras": []
            },
            "dialog": {
              "current_dial": 0,
              "pt_text": "0x0F29044C",
              "pt_dial": "0x00000000",
              "cursor_offset": null
            },
            "_t_ms": 321
          },
          {
            "active_cube": 31,
            "hero_count": 17,
            "hero_x": 4866,
            "hero_y": 512,
            "hero_z": 8324,
            "hero_beta": 2995,
            "magic_level": 3,
            "magic_point": 60,
            "magic_ball_flag": 1,
            "action_normal": 0,
            "magic_ball_index": 0,
            "magic_ball_type": 0,
            "magic_ball_count": 0,
            "magic_ball_flags": 61,
            "comportement": 1,
            "extras": {
              "active_extra_count": 0,
              "sprite_counts": {},
              "active_extras": []
            },
            "dialog": {
              "current_dial": 0,
              "pt_text": "0x0F29044C",
              "pt_dial": "0x00000000",
              "cursor_offset": null
            },
            "_t_ms": 374
          },
          {
            "active_cube": 31,
            "hero_count": 17,
            "hero_x": 4866,
            "hero_y": 512,
            "hero_z": 8324,
            "hero_beta": 2995,
            "magic_level": 3,
            "magic_point": 60,
            "magic_ball_flag": 1,
            "action_normal": 0,
            "magic_ball_index": 0,
            "magic_ball_type": 0,
            "magic_ball_count": 0,
            "magic_ball_flags": 61,
            "comportement": 1,
            "extras": {
              "active_extra_count": 0,
              "sprite_counts": {},
              "active_extras": []
            },
            "dialog": {
              "current_dial": 0,
              "pt_text": "0x0F29044C",
              "pt_dial": "0x00000000",
              "cursor_offset": null
            },
            "_t_ms": 428
          },
          {
            "active_cube": 31,
            "hero_count": 17,
            "hero_x": 4866,
            "hero_y": 512,
            "hero_z": 8324,
            "hero_beta": 2995,
            "magic_level": 3,
            "magic_point": 60,
            "magic_ball_flag": 1,
            "action_normal": 0,
            "magic_ball_index": 0,
            "magic_ball_type": 0,
            "magic_ball_count": 0,
            "magic_ball_flags": 61,
            "comportement": 1,
            "extras": {
              "active_extra_count": 0,
              "sprite_counts": {},
              "active_extras": []
            },
            "dialog": {
              "current_dial": 0,
              "pt_text": "0x0F29044C",
              "pt_dial": "0x00000000",
              "cursor_offset": null
            },
            "_t_ms": 481
          },
          {
            "active_cube": 31,
            "hero_count": 17,
            "hero_x": 4866,
            "hero_y": 512,
            "hero_z": 8324,
            "hero_beta": 2995,
            "magic_level": 3,
            "magic_point": 60,
            "magic_ball_flag": 1,
            "action_normal": 0,
            "magic_ball_index": 0,
            "magic_ball_type": 0,
            "magic_ball_count": 0,
            "magic_ball_flags": 61,
            "comportement": 1,
            "extras": {
              "active_extra_count": 0,
              "sprite_counts": {},
              "active_extras": []
            },
            "dialog": {
              "current_dial": 0,
              "pt_text": "0x0F29044C",
              "pt_dial": "0x00000000",
              "cursor_offset": null
            },
            "_t_ms": 535
          },
          {
            "active_cube": 31,
            "hero_count": 17,
            "hero_x": 4866,
            "hero_y": 512,
            "hero_z": 8324,
            "hero_beta": 2995,
            "magic_level": 3,
            "magic_point": 60,
            "magic_ball_flag": 1,
            "action_normal": 0,
            "magic_ball_index": 0,
            "magic_ball_type": 0,
            "magic_ball_count": 0,
            "magic_ball_flags": 61,
            "comportement": 1,
            "extras": {
              "active_extra_count": 0,
              "sprite_counts": {},
              "active_extras": []
            },
            "dialog": {
              "current_dial": 0,
              "pt_text": "0x0F29044C",
              "pt_dial": "0x00000000",
              "cursor_offset": null
            },
            "_t_ms": 588
          },
          {
            "active_cube": 31,
            "hero_count": 17,
            "hero_x": 4866,
            "hero_y": 512,
            "hero_z": 8324,
            "hero_beta": 2995,
            "magic_level": 3,
            "magic_point": 60,
            "magic_ball_flag": 1,
            "action_normal": 0,
            "magic_ball_index": 0,
            "magic_ball_type": 0,
            "magic_ball_count": 0,
            "magic_ball_flags": 61,
            "comportement": 1,
            "extras": {
              "active_extra_count": 0,
              "sprite_counts": {},
              "active_extras": []
            },
            "dialog": {
              "current_dial": 0,
              "pt_text": "0x0F29044C",
              "pt_dial": "0x00000000",
              "cursor_offset": null
            },
            "_t_ms": 642
          },
          {
            "active_cube": 31,
            "hero_count": 17,
            "hero_x": 4866,
            "hero_y": 512,
            "hero_z": 8324,
            "hero_beta": 2995,
            "magic_level": 3,
            "magic_point": 60,
            "magic_ball_flag": 1,
            "action_normal": 0,
            "magic_ball_index": 0,
            "magic_ball_type": 0,
            "magic_ball_count": 0,
            "magic_ball_flags": 61,
            "comportement": 1,
            "extras": {
              "active_extra_count": 0,
              "sprite_counts": {},
              "active_extras": []
            },
            "dialog": {
              "current_dial": 0,
              "pt_text": "0x0F29044C",
              "pt_dial": "0x00000000",
              "cursor_offset": null
            },
            "_t_ms": 695
          },
          {
            "active_cube": 31,
            "hero_count": 17,
            "hero_x": 4866,
            "hero_y": 512,
            "hero_z": 8324,
            "hero_beta": 2995,
            "magic_level": 3,
            "magic_point": 60,
            "magic_ball_flag": 1,
            "action_normal": 0,
            "magic_ball_index": 0,
            "magic_ball_type": 0,
            "magic_ball_count": 0,
            "magic_ball_flags": 61,
            "comportement": 1,
            "extras": {
              "active_extra_count": 0,
              "sprite_counts": {},
              "active_extras": []
            },
            "dialog": {
              "current_dial": 0,
              "pt_text": "0x0F29044C",
              "pt_dial": "0x00000000",
              "cursor_offset": null
            },
            "_t_ms": 749
          },
          {
            "active_cube": 31,
            "hero_count": 17,
            "hero_x": 4866,
            "hero_y": 512,
            "hero_z": 8324,
            "hero_beta": 2995,
            "magic_level": 3,
            "magic_point": 60,
            "magic_ball_flag": 1,
            "action_normal": 0,
            "magic_ball_index": 0,
            "magic_ball_type": 0,
            "magic_ball_count": 0,
            "magic_ball_flags": 61,
            "comportement": 1,
            "extras": {
              "active_extra_count": 0,
              "sprite_counts": {},
              "active_extras": []
            },
            "dialog": {
              "current_dial": 0,
              "pt_text": "0x0F29044C",
              "pt_dial": "0x00000000",
              "cursor_offset": null
            },
            "_t_ms": 802
          },
          {
            "active_cube": 31,
            "hero_count": 17,
            "hero_x": 4866,
            "hero_y": 512,
            "hero_z": 8324,
            "hero_beta": 2995,
            "magic_level": 3,
            "magic_point": 60,
            "magic_ball_flag": 1,
            "action_normal": 0,
            "magic_ball_index": 0,
            "magic_ball_type": 0,
            "magic_ball_count": 0,
            "magic_ball_flags": 61,
            "comportement": 1,
            "extras": {
              "active_extra_count": 0,
              "sprite_counts": {},
              "active_extras": []
            },
            "dialog": {
              "current_dial": 0,
              "pt_text": "0x0F29044C",
              "pt_dial": "0x00000000",
              "cursor_offset": null
            },
            "_t_ms": 855
          },
          {
            "active_cube": 31,
            "hero_count": 17,
            "hero_x": 4866,
            "hero_y": 512,
            "hero_z": 8324,
            "hero_beta": 2995,
            "magic_level": 3,
            "magic_point": 60,
            "magic_ball_flag": 1,
            "action_normal": 0,
            "magic_ball_index": 0,
            "magic_ball_type": 0,
            "magic_ball_count": 0,
            "magic_ball_flags": 61,
            "comportement": 1,
            "extras": {
              "active_extra_count": 0,
              "sprite_counts": {},
              "active_extras": []
            },
            "dialog": {
              "current_dial": 0,
              "pt_text": "0x0F29044C",
              "pt_dial": "0x00000000",
              "cursor_offset": null
            },
            "_t_ms": 909
          },
          {
            "active_cube": 31,
            "hero_count": 17,
            "hero_x": 4866,
            "hero_y": 512,
            "hero_z": 8324,
            "hero_beta": 2995,
            "magic_level": 3,
            "magic_point": 60,
            "magic_ball_flag": 1,
            "action_normal": 0,
            "magic_ball_index": 0,
            "magic_ball_type": 0,
            "magic_ball_count": 0,
            "magic_ball_flags": 61,
            "comportement": 1,
            "extras": {
              "active_extra_count": 0,
              "sprite_counts": {},
              "active_extras": []
            },
            "dialog": {
              "current_dial": 0,
              "pt_text": "0x0F29044C",
              "pt_dial": "0x00000000",
              "cursor_offset": null
            },
            "_t_ms": 962
          },
          {
            "active_cube": 31,
            "hero_count": 17,
            "hero_x": 4866,
            "hero_y": 512,
            "hero_z": 8324,
            "hero_beta": 2995,
            "magic_level": 3,
            "magic_point": 60,
            "magic_ball_flag": 1,
            "action_normal": 0,
            "magic_ball_index": 0,
            "magic_ball_type": 0,
            "magic_ball_count": 0,
            "magic_ball_flags": 61,
            "comportement": 1,
            "extras": {
              "active_extra_count": 0,
              "sprite_counts": {},
              "active_extras": []
            },
            "dialog": {
              "current_dial": 0,
              "pt_text": "0x0F29044C",
              "pt_dial": "0x00000000",
              "cursor_offset": null
            },
            "_t_ms": 1016
          },
          {
            "active_cube": 31,
            "hero_count": 17,
            "hero_x": 4866,
            "hero_y": 512,
            "hero_z": 8324,
            "hero_beta": 2995,
            "magic_level": 3,
            "magic_point": 60,
            "magic_ball_flag": 1,
            "action_normal": 0,
            "magic_ball_index": 0,
            "magic_ball_type": 0,
            "magic_ball_count": 0,
            "magic_ball_flags": 61,
            "comportement": 1,
            "extras": {
              "active_extra_count": 0,
              "sprite_counts": {},
              "active_extras": []
            },
            "dialog": {
              "current_dial": 0,
              "pt_text": "0x0F29044C",
              "pt_dial": "0x00000000",
              "cursor_offset": null
            },
            "_t_ms": 1070
          },
          {
            "active_cube": 31,
            "hero_count": 17,
            "hero_x": 4866,
            "hero_y": 512,
            "hero_z": 8324,
            "hero_beta": 2995,
            "magic_level": 3,
            "magic_point": 60,
            "magic_ball_flag": 1,
            "action_normal": 0,
            "magic_ball_index": 0,
            "magic_ball_type": 0,
            "magic_ball_count": 0,
            "magic_ball_flags": 61,
            "comportement": 1,
            "extras": {
              "active_extra_count": 0,
              "sprite_counts": {},
              "active_extras": []
            },
            "dialog": {
              "current_dial": 0,
              "pt_text": "0x0F29044C",
              "pt_dial": "0x00000000",
              "cursor_offset": null
            },
            "_t_ms": 1123
          },
          {
            "active_cube": 31,
            "hero_count": 17,
            "hero_x": 4866,
            "hero_y": 512,
            "hero_z": 8324,
            "hero_beta": 2995,
            "magic_level": 3,
            "magic_point": 60,
            "magic_ball_flag": 1,
            "action_normal": 0,
            "magic_ball_index": 0,
            "magic_ball_type": 0,
            "magic_ball_count": 0,
            "magic_ball_flags": 61,
            "comportement": 1,
            "extras": {
              "active_extra_count": 0,
              "sprite_counts": {},
              "active_extras": []
            },
            "dialog": {
              "current_dial": 0,
              "pt_text": "0x0F29044C",
              "pt_dial": "0x00000000",
              "cursor_offset": null
            },
            "_t_ms": 1177
          },
          {
            "active_cube": 31,
            "hero_count": 17,
            "hero_x": 4866,
            "hero_y": 512,
            "hero_z": 8324,
            "hero_beta": 2995,
            "magic_level": 3,
            "magic_point": 60,
            "magic_ball_flag": 1,
            "action_normal": 0,
            "magic_ball_index": 0,
            "magic_ball_type": 0,
            "magic_ball_count": 0,
            "magic_ball_flags": 61,
            "comportement": 1,
            "extras": {
              "active_extra_count": 0,
              "sprite_counts": {},
              "active_extras": []
            },
            "dialog": {
              "current_dial": 0,
              "pt_text": "0x0F29044C",
              "pt_dial": "0x00000000",
              "cursor_offset": null
            },
            "_t_ms": 1230
          }
        ]
      },
      "after": {
        "active_cube": 31,
        "hero_count": 17,
        "hero_x": 4866,
        "hero_y": 512,
        "hero_z": 8324,
        "hero_beta": 2995,
        "magic_level": 3,
        "magic_point": 60,
        "magic_ball_flag": 1,
        "action_normal": 0,
        "magic_ball_index": 0,
        "magic_ball_type": 0,
        "magic_ball_count": 0,
        "magic_ball_flags": 61,
        "comportement": 1
      }
    },
    {
      "action": "hold_period_0_75_sec_release",
      "before": {
        "active_cube": 31,
        "hero_count": 17,
        "hero_x": 4866,
        "hero_y": 512,
        "hero_z": 8324,
        "hero_beta": 2995,
        "magic_level": 3,
        "magic_point": 60,
        "magic_ball_flag": 1,
        "action_normal": 0,
        "magic_ball_index": 0,
        "magic_ball_type": 0,
        "magic_ball_count": 0,
        "magic_ball_flags": 61,
        "comportement": 1
      },
      "poll": {
        "sample_count": 36,
        "duration_ms": 2163,
        "changed_fields": {
          "extras": [
            {
              "active_extra_count": 0,
              "sprite_counts": {},
              "active_extras": []
            },
            {
              "active_extra_count": 1,
              "sprite_counts": {
                "10": 1
              },
              "active_extras": [
                {
                  "index": 0,
                  "sprite": 10,
                  "body": -1,
                  "pos_x": 4763,
                  "pos_y": 1725,
                  "pos_z": 8312,
                  "owner": 0,
                  "hit_force": 30
                }
              ]
            },
            {
              "active_extra_count": 1,
              "sprite_counts": {
                "10": 1
              },
              "active_extras": [
                {
                  "index": 0,
                  "sprite": 10,
                  "body": -1,
                  "pos_x": 4557,
                  "pos_y": 1744,
                  "pos_z": 8288,
                  "owner": 0,
                  "hit_force": 30
                }
              ]
            },
            {
              "active_extra_count": 1,
              "sprite_counts": {
                "10": 1
              },
              "active_extras": [
                {
                  "index": 0,
                  "sprite": 10,
                  "body": -1,
                  "pos_x": 4248,
                  "pos_y": 1759,
                  "pos_z": 8252,
                  "owner": 0,
                  "hit_force": 30
                }
              ]
            },
            {
              "active_extra_count": 1,
              "sprite_counts": {
                "10": 1
              },
              "active_extras": [
                {
                  "index": 0,
                  "sprite": 10,
                  "body": -1,
                  "pos_x": 3939,
                  "pos_y": 1759,
                  "pos_z": 8216,
                  "owner": 0,
                  "hit_force": 30
                }
              ]
            },
            {
              "active_extra_count": 1,
              "sprite_counts": {
                "10": 1
              },
              "active_extras": [
                {
                  "index": 0,
                  "sprite": 10,
                  "body": -1,
                  "pos_x": 3733,
                  "pos_y": 1750,
                  "pos_z": 8192,
                  "owner": 0,
                  "hit_force": 30
                }
              ]
            },
            {
              "active_extra_count": 1,
              "sprite_counts": {
                "10": 1
              },
              "active_extras": [
                {
                  "index": 0,
                  "sprite": 10,
                  "body": -1,
                  "pos_x": 3424,
                  "pos_y": 1723,
                  "pos_z": 8156,
                  "owner": 0,
                  "hit_force": 30
                }
              ]
            },
            {
              "active_extra_count": 1,
              "sprite_counts": {
                "10": 1
              },
              "active_extras": [
                {
                  "index": 0,
                  "sprite": 10,
                  "body": -1,
                  "pos_x": 3115,
                  "pos_y": 1681,
                  "pos_z": 8120,
                  "owner": 0,
                  "hit_force": 30
                }
              ]
            }
          ],
          "magic_point": [
            60,
            59
          ]
        },
        "samples": [
          {
            "active_cube": 31,
            "hero_count": 17,
            "hero_x": 4866,
            "hero_y": 512,
            "hero_z": 8324,
            "hero_beta": 2995,
            "magic_level": 3,
            "magic_point": 60,
            "magic_ball_flag": 1,
            "action_normal": 0,
            "magic_ball_index": 0,
            "magic_ball_type": 0,
            "magic_ball_count": 0,
            "magic_ball_flags": 61,
            "comportement": 1,
            "extras": {
              "active_extra_count": 0,
              "sprite_counts": {},
              "active_extras": []
            },
            "dialog": {
              "current_dial": 0,
              "pt_text": "0x0F29044C",
              "pt_dial": "0x00000000",
              "cursor_offset": null
            },
            "_t_ms": 51
          },
          {
            "active_cube": 31,
            "hero_count": 17,
            "hero_x": 4866,
            "hero_y": 512,
            "hero_z": 8324,
            "hero_beta": 2995,
            "magic_level": 3,
            "magic_point": 60,
            "magic_ball_flag": 1,
            "action_normal": 0,
            "magic_ball_index": 0,
            "magic_ball_type": 0,
            "magic_ball_count": 0,
            "magic_ball_flags": 61,
            "comportement": 1,
            "extras": {
              "active_extra_count": 0,
              "sprite_counts": {},
              "active_extras": []
            },
            "dialog": {
              "current_dial": 0,
              "pt_text": "0x0F29044C",
              "pt_dial": "0x00000000",
              "cursor_offset": null
            },
            "_t_ms": 105
          },
          {
            "active_cube": 31,
            "hero_count": 17,
            "hero_x": 4866,
            "hero_y": 512,
            "hero_z": 8324,
            "hero_beta": 2995,
            "magic_level": 3,
            "magic_point": 60,
            "magic_ball_flag": 1,
            "action_normal": 0,
            "magic_ball_index": 0,
            "magic_ball_type": 0,
            "magic_ball_count": 0,
            "magic_ball_flags": 61,
            "comportement": 1,
            "extras": {
              "active_extra_count": 0,
              "sprite_counts": {},
              "active_extras": []
            },
            "dialog": {
              "current_dial": 0,
              "pt_text": "0x0F29044C",
              "pt_dial": "0x00000000",
              "cursor_offset": null
            },
            "_t_ms": 159
          },
          {
            "active_cube": 31,
            "hero_count": 17,
            "hero_x": 4866,
            "hero_y": 512,
            "hero_z": 8324,
            "hero_beta": 2995,
            "magic_level": 3,
            "magic_point": 60,
            "magic_ball_flag": 1,
            "action_normal": 0,
            "magic_ball_index": 0,
            "magic_ball_type": 0,
            "magic_ball_count": 0,
            "magic_ball_flags": 61,
            "comportement": 1,
            "extras": {
              "active_extra_count": 0,
              "sprite_counts": {},
              "active_extras": []
            },
            "dialog": {
              "current_dial": 0,
              "pt_text": "0x0F29044C",
              "pt_dial": "0x00000000",
              "cursor_offset": null
            },
            "_t_ms": 214
          },
          {
            "active_cube": 31,
            "hero_count": 17,
            "hero_x": 4866,
            "hero_y": 512,
            "hero_z": 8324,
            "hero_beta": 2995,
            "magic_level": 3,
            "magic_point": 60,
            "magic_ball_flag": 1,
            "action_normal": 0,
            "magic_ball_index": 0,
            "magic_ball_type": 0,
            "magic_ball_count": 0,
            "magic_ball_flags": 61,
            "comportement": 1,
            "extras": {
              "active_extra_count": 0,
              "sprite_counts": {},
              "active_extras": []
            },
            "dialog": {
              "current_dial": 0,
              "pt_text": "0x0F29044C",
              "pt_dial": "0x00000000",
              "cursor_offset": null
            },
            "_t_ms": 267
          },
          {
            "active_cube": 31,
            "hero_count": 17,
            "hero_x": 4866,
            "hero_y": 512,
            "hero_z": 8324,
            "hero_beta": 2995,
            "magic_level": 3,
            "magic_point": 60,
            "magic_ball_flag": 1,
            "action_normal": 0,
            "magic_ball_index": 0,
            "magic_ball_type": 0,
            "magic_ball_count": 0,
            "magic_ball_flags": 61,
            "comportement": 1,
            "extras": {
              "active_extra_count": 0,
              "sprite_counts": {},
              "active_extras": []
            },
            "dialog": {
              "current_dial": 0,
              "pt_text": "0x0F29044C",
              "pt_dial": "0x00000000",
              "cursor_offset": null
            },
            "_t_ms": 321
          },
          {
            "active_cube": 31,
            "hero_count": 17,
            "hero_x": 4866,
            "hero_y": 512,
            "hero_z": 8324,
            "hero_beta": 2995,
            "magic_level": 3,
            "magic_point": 60,
            "magic_ball_flag": 1,
            "action_normal": 0,
            "magic_ball_index": 0,
            "magic_ball_type": 0,
            "magic_ball_count": 0,
            "magic_ball_flags": 61,
            "comportement": 1,
            "extras": {
              "active_extra_count": 0,
              "sprite_counts": {},
              "active_extras": []
            },
            "dialog": {
              "current_dial": 0,
              "pt_text": "0x0F29044C",
              "pt_dial": "0x00000000",
              "cursor_offset": null
            },
            "_t_ms": 374
          },
          {
            "active_cube": 31,
            "hero_count": 17,
            "hero_x": 4866,
            "hero_y": 512,
            "hero_z": 8324,
            "hero_beta": 2995,
            "magic_level": 3,
            "magic_point": 60,
            "magic_ball_flag": 1,
            "action_normal": 0,
            "magic_ball_index": 0,
            "magic_ball_type": 0,
            "magic_ball_count": 0,
            "magic_ball_flags": 61,
            "comportement": 1,
            "extras": {
              "active_extra_count": 0,
              "sprite_counts": {},
              "active_extras": []
            },
            "dialog": {
              "current_dial": 0,
              "pt_text": "0x0F29044C",
              "pt_dial": "0x00000000",
              "cursor_offset": null
            },
            "_t_ms": 427
          },
          {
            "active_cube": 31,
            "hero_count": 17,
            "hero_x": 4866,
            "hero_y": 512,
            "hero_z": 8324,
            "hero_beta": 2995,
            "magic_level": 3,
            "magic_point": 60,
            "magic_ball_flag": 1,
            "action_normal": 0,
            "magic_ball_index": 0,
            "magic_ball_type": 0,
            "magic_ball_count": 0,
            "magic_ball_flags": 61,
            "comportement": 1,
            "extras": {
              "active_extra_count": 0,
              "sprite_counts": {},
              "active_extras": []
            },
            "dialog": {
              "current_dial": 0,
              "pt_text": "0x0F29044C",
              "pt_dial": "0x00000000",
              "cursor_offset": null
            },
            "_t_ms": 481
          },
          {
            "active_cube": 31,
            "hero_count": 17,
            "hero_x": 4866,
            "hero_y": 512,
            "hero_z": 8324,
            "hero_beta": 2995,
            "magic_level": 3,
            "magic_point": 60,
            "magic_ball_flag": 1,
            "action_normal": 0,
            "magic_ball_index": 0,
            "magic_ball_type": 0,
            "magic_ball_count": 0,
            "magic_ball_flags": 61,
            "comportement": 1,
            "extras": {
              "active_extra_count": 0,
              "sprite_counts": {},
              "active_extras": []
            },
            "dialog": {
              "current_dial": 0,
              "pt_text": "0x0F29044C",
              "pt_dial": "0x00000000",
              "cursor_offset": null
            },
            "_t_ms": 535
          },
          {
            "active_cube": 31,
            "hero_count": 17,
            "hero_x": 4866,
            "hero_y": 512,
            "hero_z": 8324,
            "hero_beta": 2995,
            "magic_level": 3,
            "magic_point": 60,
            "magic_ball_flag": 1,
            "action_normal": 0,
            "magic_ball_index": 0,
            "magic_ball_type": 0,
            "magic_ball_count": 0,
            "magic_ball_flags": 61,
            "comportement": 1,
            "extras": {
              "active_extra_count": 0,
              "sprite_counts": {},
              "active_extras": []
            },
            "dialog": {
              "current_dial": 0,
              "pt_text": "0x0F29044C",
              "pt_dial": "0x00000000",
              "cursor_offset": null
            },
            "_t_ms": 588
          },
          {
            "active_cube": 31,
            "hero_count": 17,
            "hero_x": 4866,
            "hero_y": 512,
            "hero_z": 8324,
            "hero_beta": 2995,
            "magic_level": 3,
            "magic_point": 60,
            "magic_ball_flag": 1,
            "action_normal": 0,
            "magic_ball_index": 0,
            "magic_ball_type": 0,
            "magic_ball_count": 0,
            "magic_ball_flags": 61,
            "comportement": 1,
            "extras": {
              "active_extra_count": 0,
              "sprite_counts": {},
              "active_extras": []
            },
            "dialog": {
              "current_dial": 0,
              "pt_text": "0x0F29044C",
              "pt_dial": "0x00000000",
              "cursor_offset": null
            },
            "_t_ms": 641
          },
          {
            "active_cube": 31,
            "hero_count": 17,
            "hero_x": 4866,
            "hero_y": 512,
            "hero_z": 8324,
            "hero_beta": 2995,
            "magic_level": 3,
            "magic_point": 59,
            "magic_ball_flag": 1,
            "action_normal": 0,
            "magic_ball_index": 0,
            "magic_ball_type": 0,
            "magic_ball_count": 0,
            "magic_ball_flags": 61,
            "comportement": 1,
            "extras": {
              "active_extra_count": 1,
              "sprite_counts": {
                "10": 1
              },
              "active_extras": [
                {
                  "index": 0,
                  "sprite": 10,
                  "body": -1,
                  "pos_x": 4763,
                  "pos_y": 1725,
                  "pos_z": 8312,
                  "owner": 0,
                  "hit_force": 30
                }
              ]
            },
            "dialog": {
              "current_dial": 0,
              "pt_text": "0x0F29044C",
              "pt_dial": "0x00000000",
              "cursor_offset": null
            },
            "_t_ms": 695
          },
          {
            "active_cube": 31,
            "hero_count": 17,
            "hero_x": 4866,
            "hero_y": 512,
            "hero_z": 8324,
            "hero_beta": 2995,
            "magic_level": 3,
            "magic_point": 59,
            "magic_ball_flag": 1,
            "action_normal": 0,
            "magic_ball_index": 0,
            "magic_ball_type": 0,
            "magic_ball_count": 0,
            "magic_ball_flags": 61,
            "comportement": 1,
            "extras": {
              "active_extra_count": 1,
              "sprite_counts": {
                "10": 1
              },
              "active_extras": [
                {
                  "index": 0,
                  "sprite": 10,
                  "body": -1,
                  "pos_x": 4557,
                  "pos_y": 1744,
                  "pos_z": 8288,
                  "owner": 0,
                  "hit_force": 30
                }
              ]
            },
            "dialog": {
              "current_dial": 0,
              "pt_text": "0x0F29044C",
              "pt_dial": "0x00000000",
              "cursor_offset": null
            },
            "_t_ms": 749
          },
          {
            "active_cube": 31,
            "hero_count": 17,
            "hero_x": 4866,
            "hero_y": 512,
            "hero_z": 8324,
            "hero_beta": 2995,
            "magic_level": 3,
            "magic_point": 59,
            "magic_ball_flag": 1,
            "action_normal": 0,
            "magic_ball_index": 0,
            "magic_ball_type": 0,
            "magic_ball_count": 0,
            "magic_ball_flags": 61,
            "comportement": 1,
            "extras": {
              "active_extra_count": 1,
              "sprite_counts": {
                "10": 1
              },
              "active_extras": [
                {
                  "index": 0,
                  "sprite": 10,
                  "body": -1,
                  "pos_x": 4248,
                  "pos_y": 1759,
                  "pos_z": 8252,
                  "owner": 0,
                  "hit_force": 30
                }
              ]
            },
            "dialog": {
              "current_dial": 0,
              "pt_text": "0x0F29044C",
              "pt_dial": "0x00000000",
              "cursor_offset": null
            },
            "_t_ms": 803
          },
          {
            "active_cube": 31,
            "hero_count": 17,
            "hero_x": 4866,
            "hero_y": 512,
            "hero_z": 8324,
            "hero_beta": 2995,
            "magic_level": 3,
            "magic_point": 59,
            "magic_ball_flag": 1,
            "action_normal": 0,
            "magic_ball_index": 0,
            "magic_ball_type": 0,
            "magic_ball_count": 0,
            "magic_ball_flags": 61,
            "comportement": 1,
            "extras": {
              "active_extra_count": 1,
              "sprite_counts": {
                "10": 1
              },
              "active_extras": [
                {
                  "index": 0,
                  "sprite": 10,
                  "body": -1,
                  "pos_x": 3939,
                  "pos_y": 1759,
                  "pos_z": 8216,
                  "owner": 0,
                  "hit_force": 30
                }
              ]
            },
            "dialog": {
              "current_dial": 0,
              "pt_text": "0x0F29044C",
              "pt_dial": "0x00000000",
              "cursor_offset": null
            },
            "_t_ms": 858
          },
          {
            "active_cube": 31,
            "hero_count": 17,
            "hero_x": 4866,
            "hero_y": 512,
            "hero_z": 8324,
            "hero_beta": 2995,
            "magic_level": 3,
            "magic_point": 59,
            "magic_ball_flag": 1,
            "action_normal": 0,
            "magic_ball_index": 0,
            "magic_ball_type": 0,
            "magic_ball_count": 0,
            "magic_ball_flags": 61,
            "comportement": 1,
            "extras": {
              "active_extra_count": 1,
              "sprite_counts": {
                "10": 1
              },
              "active_extras": [
                {
                  "index": 0,
                  "sprite": 10,
                  "body": -1,
                  "pos_x": 3733,
                  "pos_y": 1750,
                  "pos_z": 8192,
                  "owner": 0,
                  "hit_force": 30
                }
              ]
            },
            "dialog": {
              "current_dial": 0,
              "pt_text": "0x0F29044C",
              "pt_dial": "0x00000000",
              "cursor_offset": null
            },
            "_t_ms": 912
          },
          {
            "active_cube": 31,
            "hero_count": 17,
            "hero_x": 4866,
            "hero_y": 512,
            "hero_z": 8324,
            "hero_beta": 2995,
            "magic_level": 3,
            "magic_point": 59,
            "magic_ball_flag": 1,
            "action_normal": 0,
            "magic_ball_index": 0,
            "magic_ball_type": 0,
            "magic_ball_count": 0,
            "magic_ball_flags": 61,
            "comportement": 1,
            "extras": {
              "active_extra_count": 1,
              "sprite_counts": {
                "10": 1
              },
              "active_extras": [
                {
                  "index": 0,
                  "sprite": 10,
                  "body": -1,
                  "pos_x": 3424,
                  "pos_y": 1723,
                  "pos_z": 8156,
                  "owner": 0,
                  "hit_force": 30
                }
              ]
            },
            "dialog": {
              "current_dial": 0,
              "pt_text": "0x0F29044C",
              "pt_dial": "0x00000000",
              "cursor_offset": null
            },
            "_t_ms": 965
          },
          {
            "active_cube": 31,
            "hero_count": 17,
            "hero_x": 4866,
            "hero_y": 512,
            "hero_z": 8324,
            "hero_beta": 2995,
            "magic_level": 3,
            "magic_point": 59,
            "magic_ball_flag": 1,
            "action_normal": 0,
            "magic_ball_index": 0,
            "magic_ball_type": 0,
            "magic_ball_count": 0,
            "magic_ball_flags": 61,
            "comportement": 1,
            "extras": {
              "active_extra_count": 1,
              "sprite_counts": {
                "10": 1
              },
              "active_extras": [
                {
                  "index": 0,
                  "sprite": 10,
                  "body": -1,
                  "pos_x": 3115,
                  "pos_y": 1681,
                  "pos_z": 8120,
                  "owner": 0,
                  "hit_force": 30
                }
              ]
            },
            "dialog": {
              "current_dial": 0,
              "pt_text": "0x0F29044C",
              "pt_dial": "0x00000000",
              "cursor_offset": null
            },
            "_t_ms": 1018
          },
          {
            "active_cube": 31,
            "hero_count": 17,
            "hero_x": 4866,
            "hero_y": 512,
            "hero_z": 8324,
            "hero_beta": 2995,
            "magic_level": 3,
            "magic_point": 59,
            "magic_ball_flag": 1,
            "action_normal": 0,
            "magic_ball_index": 0,
            "magic_ball_type": 0,
            "magic_ball_count": 0,
            "magic_ball_flags": 61,
            "comportement": 1,
            "extras": {
              "active_extra_count": 1,
              "sprite_counts": {
                "10": 1
              },
              "active_extras": [
                {
                  "index": 0,
                  "sprite": 10,
                  "body": -1,
                  "pos_x": 2909,
                  "pos_y": 1644,
                  "pos_z": 8096,
                  "owner": 0,
                  "hit_force": 30
                }
              ]
            },
            "dialog": {
              "current_dial": 0,
              "pt_text": "0x0F29044C",
              "pt_dial": "0x00000000",
              "cursor_offset": null
            },
            "_t_ms": 1073
          },
          {
            "active_cube": 31,
            "hero_count": 17,
            "hero_x": 4866,
            "hero_y": 512,
            "hero_z": 8324,
            "hero_beta": 2995,
            "magic_level": 3,
            "magic_point": 59,
            "magic_ball_flag": 1,
            "action_normal": 0,
            "magic_ball_index": 0,
            "magic_ball_type": 0,
            "magic_ball_count": 0,
            "magic_ball_flags": 61,
            "comportement": 1,
            "extras": {
              "active_extra_count": 1,
              "sprite_counts": {
                "14": 1
              },
              "active_extras": [
                {
                  "index": 1,
                  "sprite": 14,
                  "body": -1,
                  "pos_x": 2720,
                  "pos_y": 1551,
                  "pos_z": 8072,
                  "owner": 255,
                  "hit_force": 0
                }
              ]
            },
            "dialog": {
              "current_dial": 0,
              "pt_text": "0x0F29044C",
              "pt_dial": "0x00000000",
              "cursor_offset": null
            },
            "_t_ms": 1127
          },
          {
            "active_cube": 31,
            "hero_count": 17,
            "hero_x": 4866,
            "hero_y": 512,
            "hero_z": 8324,
            "hero_beta": 2995,
            "magic_level": 3,
            "magic_point": 59,
            "magic_ball_flag": 1,
            "action_normal": 0,
            "magic_ball_index": 0,
            "magic_ball_type": 0,
            "magic_ball_count": 0,
            "magic_ball_flags": 61,
            "comportement": 1,
            "extras": {
              "active_extra_count": 1,
              "sprite_counts": {
                "14": 1
              },
              "active_extras": [
                {
                  "index": 1,
                  "sprite": 14,
                  "body": -1,
                  "pos_x": 3250,
                  "pos_y": 1445,
                  "pos_z": 8125,
                  "owner": 255,
                  "hit_force": 0
                }
              ]
            },
            "dialog": {
              "current_dial": 0,
              "pt_text": "0x0F29044C",
              "pt_dial": "0x00000000",
              "cursor_offset": null
            },
            "_t_ms": 1180
          },
          {
            "active_cube": 31,
            "hero_count": 17,
            "hero_x": 4866,
            "hero_y": 512,
            "hero_z": 8324,
            "hero_beta": 2995,
            "magic_level": 3,
            "magic_point": 59,
            "magic_ball_flag": 1,
            "action_normal": 0,
            "magic_ball_index": 0,
            "magic_ball_type": 0,
            "magic_ball_count": 0,
            "magic_ball_flags": 61,
            "comportement": 1,
            "extras": {
              "active_extra_count": 1,
              "sprite_counts": {
                "14": 1
              },
              "active_extras": [
                {
                  "index": 1,
                  "sprite": 14,
                  "body": -1,
                  "pos_x": 3780,
                  "pos_y": 1339,
                  "pos_z": 8178,
                  "owner": 255,
                  "hit_force": 0
                }
              ]
            },
            "dialog": {
              "current_dial": 0,
              "pt_text": "0x0F29044C",
              "pt_dial": "0x00000000",
              "cursor_offset": null
            },
            "_t_ms": 1233
          },
          {
            "active_cube": 31,
            "hero_count": 17,
            "hero_x": 4866,
            "hero_y": 512,
            "hero_z": 8324,
            "hero_beta": 2995,
            "magic_level": 3,
            "magic_point": 59,
            "magic_ball_flag": 1,
            "action_normal": 0,
            "magic_ball_index": 0,
            "magic_ball_type": 0,
            "magic_ball_count": 0,
            "magic_ball_flags": 61,
            "comportement": 1,
            "extras": {
              "active_extra_count": 1,
              "sprite_counts": {
                "14": 1
              },
              "active_extras": [
                {
                  "index": 1,
                  "sprite": 14,
                  "body": -1,
                  "pos_x": 4320,
                  "pos_y": 1231,
                  "pos_z": 8241,
                  "owner": 255,
                  "hit_force": 0
                }
              ]
            },
            "dialog": {
              "current_dial": 0,
              "pt_text": "0x0F29044C",
              "pt_dial": "0x00000000",
              "cursor_offset": null
            },
            "_t_ms": 1286
          },
          {
            "active_cube": 31,
            "hero_count": 17,
            "hero_x": 4866,
            "hero_y": 512,
            "hero_z": 8324,
            "hero_beta": 2995,
            "magic_level": 3,
            "magic_point": 59,
            "magic_ball_flag": 1,
            "action_normal": 0,
            "magic_ball_index": 0,
            "magic_ball_type": 0,
            "magic_ball_count": 0,
            "magic_ball_flags": 61,
            "comportement": 1,
            "extras": {
              "active_extra_count": 0,
              "sprite_counts": {},
              "active_extras": []
            },
            "dialog": {
              "current_dial": 0,
              "pt_text": "0x0F29044C",
              "pt_dial": "0x00000000",
              "cursor_offset": null
            },
            "_t_ms": 1340
          },
          {
            "active_cube": 31,
            "hero_count": 17,
            "hero_x": 4866,
            "hero_y": 512,
            "hero_z": 8324,
            "hero_beta": 2995,
            "magic_level": 3,
            "magic_point": 59,
            "magic_ball_flag": 1,
            "action_normal": 0,
            "magic_ball_index": 0,
            "magic_ball_type": 0,
            "magic_ball_count": 0,
            "magic_ball_flags": 61,
            "comportement": 1,
            "extras": {
              "active_extra_count": 0,
              "sprite_counts": {},
              "active_extras": []
            },
            "dialog": {
              "current_dial": 0,
              "pt_text": "0x0F29044C",
              "pt_dial": "0x00000000",
              "cursor_offset": null
            },
            "_t_ms": 1393
          },
          {
            "active_cube": 31,
            "hero_count": 17,
            "hero_x": 4866,
            "hero_y": 512,
            "hero_z": 8324,
            "hero_beta": 2995,
            "magic_level": 3,
            "magic_point": 59,
            "magic_ball_flag": 1,
            "action_normal": 0,
            "magic_ball_index": 0,
            "magic_ball_type": 0,
            "magic_ball_count": 0,
            "magic_ball_flags": 61,
            "comportement": 1,
            "extras": {
              "active_extra_count": 0,
              "sprite_counts": {},
              "active_extras": []
            },
            "dialog": {
              "current_dial": 0,
              "pt_text": "0x0F29044C",
              "pt_dial": "0x00000000",
              "cursor_offset": null
            },
            "_t_ms": 1447
          },
          {
            "active_cube": 31,
            "hero_count": 17,
            "hero_x": 4866,
            "hero_y": 512,
            "hero_z": 8324,
            "hero_beta": 2995,
            "magic_level": 3,
            "magic_point": 59,
            "magic_ball_flag": 1,
            "action_normal": 0,
            "magic_ball_index": 0,
            "magic_ball_type": 0,
            "magic_ball_count": 0,
            "magic_ball_flags": 61,
            "comportement": 1,
            "extras": {
              "active_extra_count": 0,
              "sprite_counts": {},
              "active_extras": []
            },
            "dialog": {
              "current_dial": 0,
              "pt_text": "0x0F29044C",
              "pt_dial": "0x00000000",
              "cursor_offset": null
            },
            "_t_ms": 1500
          },
          {
            "active_cube": 31,
            "hero_count": 17,
            "hero_x": 4866,
            "hero_y": 512,
            "hero_z": 8324,
            "hero_beta": 2995,
            "magic_level": 3,
            "magic_point": 59,
            "magic_ball_flag": 1,
            "action_normal": 0,
            "magic_ball_index": 0,
            "magic_ball_type": 0,
            "magic_ball_count": 0,
            "magic_ball_flags": 61,
            "comportement": 1,
            "extras": {
              "active_extra_count": 0,
              "sprite_counts": {},
              "active_extras": []
            },
            "dialog": {
              "current_dial": 0,
              "pt_text": "0x0F29044C",
              "pt_dial": "0x00000000",
              "cursor_offset": null
            },
            "_t_ms": 1553
          },
          {
            "active_cube": 31,
            "hero_count": 17,
            "hero_x": 4866,
            "hero_y": 512,
            "hero_z": 8324,
            "hero_beta": 2995,
            "magic_level": 3,
            "magic_point": 59,
            "magic_ball_flag": 1,
            "action_normal": 0,
            "magic_ball_index": 0,
            "magic_ball_type": 0,
            "magic_ball_count": 0,
            "magic_ball_flags": 61,
            "comportement": 1,
            "extras": {
              "active_extra_count": 0,
              "sprite_counts": {},
              "active_extras": []
            },
            "dialog": {
              "current_dial": 0,
              "pt_text": "0x0F29044C",
              "pt_dial": "0x00000000",
              "cursor_offset": null
            },
            "_t_ms": 1607
          },
          {
            "active_cube": 31,
            "hero_count": 17,
            "hero_x": 4866,
            "hero_y": 512,
            "hero_z": 8324,
            "hero_beta": 2995,
            "magic_level": 3,
            "magic_point": 59,
            "magic_ball_flag": 1,
            "action_normal": 0,
            "magic_ball_index": 0,
            "magic_ball_type": 0,
            "magic_ball_count": 0,
            "magic_ball_flags": 61,
            "comportement": 1,
            "extras": {
              "active_extra_count": 0,
              "sprite_counts": {},
              "active_extras": []
            },
            "dialog": {
              "current_dial": 0,
              "pt_text": "0x0F29044C",
              "pt_dial": "0x00000000",
              "cursor_offset": null
            },
            "_t_ms": 1661
          },
          {
            "active_cube": 31,
            "hero_count": 17,
            "hero_x": 4866,
            "hero_y": 512,
            "hero_z": 8324,
            "hero_beta": 2995,
            "magic_level": 3,
            "magic_point": 59,
            "magic_ball_flag": 1,
            "action_normal": 0,
            "magic_ball_index": 0,
            "magic_ball_type": 0,
            "magic_ball_count": 0,
            "magic_ball_flags": 61,
            "comportement": 1,
            "extras": {
              "active_extra_count": 0,
              "sprite_counts": {},
              "active_extras": []
            },
            "dialog": {
              "current_dial": 0,
              "pt_text": "0x0F29044C",
              "pt_dial": "0x00000000",
              "cursor_offset": null
            },
            "_t_ms": 1714
          },
          {
            "active_cube": 31,
            "hero_count": 17,
            "hero_x": 4866,
            "hero_y": 512,
            "hero_z": 8324,
            "hero_beta": 2995,
            "magic_level": 3,
            "magic_point": 59,
            "magic_ball_flag": 1,
            "action_normal": 0,
            "magic_ball_index": 0,
            "magic_ball_type": 0,
            "magic_ball_count": 0,
            "magic_ball_flags": 61,
            "comportement": 1,
            "extras": {
              "active_extra_count": 0,
              "sprite_counts": {},
              "active_extras": []
            },
            "dialog": {
              "current_dial": 0,
              "pt_text": "0x0F29044C",
              "pt_dial": "0x00000000",
              "cursor_offset": null
            },
            "_t_ms": 1768
          },
          {
            "active_cube": 31,
            "hero_count": 17,
            "hero_x": 4866,
            "hero_y": 512,
            "hero_z": 8324,
            "hero_beta": 2995,
            "magic_level": 3,
            "magic_point": 59,
            "magic_ball_flag": 1,
            "action_normal": 0,
            "magic_ball_index": 0,
            "magic_ball_type": 0,
            "magic_ball_count": 0,
            "magic_ball_flags": 61,
            "comportement": 1,
            "extras": {
              "active_extra_count": 0,
              "sprite_counts": {},
              "active_extras": []
            },
            "dialog": {
              "current_dial": 0,
              "pt_text": "0x0F29044C",
              "pt_dial": "0x00000000",
              "cursor_offset": null
            },
            "_t_ms": 1822
          },
          {
            "active_cube": 31,
            "hero_count": 17,
            "hero_x": 4866,
            "hero_y": 512,
            "hero_z": 8324,
            "hero_beta": 2995,
            "magic_level": 3,
            "magic_point": 59,
            "magic_ball_flag": 1,
            "action_normal": 0,
            "magic_ball_index": 0,
            "magic_ball_type": 0,
            "magic_ball_count": 0,
            "magic_ball_flags": 61,
            "comportement": 1,
            "extras": {
              "active_extra_count": 0,
              "sprite_counts": {},
              "active_extras": []
            },
            "dialog": {
              "current_dial": 0,
              "pt_text": "0x0F29044C",
              "pt_dial": "0x00000000",
              "cursor_offset": null
            },
            "_t_ms": 1876
          },
          {
            "active_cube": 31,
            "hero_count": 17,
            "hero_x": 4866,
            "hero_y": 512,
            "hero_z": 8324,
            "hero_beta": 2995,
            "magic_level": 3,
            "magic_point": 59,
            "magic_ball_flag": 1,
            "action_normal": 0,
            "magic_ball_index": 0,
            "magic_ball_type": 0,
            "magic_ball_count": 0,
            "magic_ball_flags": 61,
            "comportement": 1,
            "extras": {
              "active_extra_count": 0,
              "sprite_counts": {},
              "active_extras": []
            },
            "dialog": {
              "current_dial": 0,
              "pt_text": "0x0F29044C",
              "pt_dial": "0x00000000",
              "cursor_offset": null
            },
            "_t_ms": 1929
          }
        ]
      },
      "after": {
        "active_cube": 31,
        "hero_count": 17,
        "hero_x": 4866,
        "hero_y": 512,
        "hero_z": 8324,
        "hero_beta": 2995,
        "magic_level": 3,
        "magic_point": 59,
        "magic_ball_flag": 1,
        "action_normal": 0,
        "magic_ball_index": 0,
        "magic_ball_type": 0,
        "magic_ball_count": 0,
        "magic_ball_flags": 61,
        "comportement": 1
      }
    }
  ],
  "after_actions_screenshot": "work/game_drive_capability_ladder/runs/capability_magic_ball_throw_20260503T155502Z/after_actions.png",
  "runtime_final": {
    "active_cube": 31,
    "hero_count": 17,
    "hero_x": 4866,
    "hero_y": 512,
    "hero_z": 8324,
    "hero_beta": 2995,
    "magic_level": 3,
    "magic_point": 59,
    "magic_ball_flag": 1,
    "action_normal": 0,
    "magic_ball_index": 0,
    "magic_ball_type": 0,
    "magic_ball_count": 0,
    "magic_ball_flags": 61,
    "comportement": 1
  },
  "evidence_archive": {
    "archive_id": "magic-ball-live-window-20260503-magic_ball_throw-capability_magic_ball_throw_20260503T155502Z",
    "manifest": "docs/evidence_archive/game_drive/magic-ball-live-window-20260503-magic_ball_throw-capability_magic_ball_throw_20260503T155502Z/manifest.json",
    "reason": "capability_failure:blocked"
  }
}