{
  "post_stream": {
    "posts": [
      {
        "id": 7914,
        "name": null,
        "username": "Blafards61",
        "avatar_template": "/user_avatar/forum.magicball.net/blafards61/{size}/32_2.png",
        "created_at": "2004-12-30T20:36:59.000Z",
        "cooked": "<p>Hi there,i played to A Clones life and I LOVED IT because we were another character and everything was different.So I ask for that.<br>\nIs that possible to be Zoe or a Blafard?<br>\nThanks in advance</p>",
        "post_number": 1,
        "post_type": 1,
        "posts_count": 34,
        "updated_at": "2024-10-25T15:22:23.253Z",
        "reply_count": 13,
        "reply_to_post_number": null,
        "quote_count": 0,
        "incoming_link_count": 7,
        "reads": 0,
        "readers_count": 0,
        "score": 100.0,
        "yours": false,
        "topic_id": 7911,
        "topic_slug": "is-there-a-lba-that-we-play-as-zoe",
        "display_username": null,
        "primary_group_name": null,
        "flair_name": null,
        "flair_url": null,
        "flair_bg_color": null,
        "flair_color": null,
        "flair_group_id": null,
        "badges_granted": [],
        "version": 1,
        "can_edit": false,
        "can_delete": false,
        "can_recover": false,
        "can_see_hidden_post": false,
        "can_wiki": false,
        "read": false,
        "user_title": null,
        "bookmarked": false,
        "actions_summary": [
          {
            "id": 2,
            "can_act": true
          },
          {
            "id": 6,
            "can_act": true
          },
          {
            "id": 3,
            "can_act": true
          },
          {
            "id": 4,
            "can_act": true
          },
          {
            "id": 8,
            "can_act": true
          },
          {
            "id": 10,
            "can_act": true
          },
          {
            "id": 7,
            "can_act": true
          }
        ],
        "moderator": false,
        "admin": false,
        "staff": false,
        "user_id": 1285,
        "hidden": false,
        "trust_level": 1,
        "deleted_at": null,
        "user_deleted": false,
        "edit_reason": null,
        "can_view_edit_history": false,
        "wiki": false,
        "post_url": "/t/is-there-a-lba-that-we-play-as-zoe/7911/1",
        "reactions": [],
        "current_user_reaction": null,
        "reaction_users_count": 0,
        "current_user_used_main_reaction": false,
        "can_accept_answer": false,
        "can_unaccept_answer": false,
        "accepted_answer": false,
        "topic_accepted_answer": null,
        "can_vote": false
      },
      {
        "id": 205781,
        "name": null,
        "username": "ChaosFish",
        "avatar_template": "/user_avatar/forum.magicball.net/chaosfish/{size}/2_2.png",
        "created_at": "2004-12-30T20:38:28.000Z",
        "cooked": "<p>Yes, use LBA Package Editor and replace Twinsens model with Zoes model.<br>\nCheck the quick start and information thread.</p>\n<p>Oh and, WELCOME to the MBN!! <img src=\"//forum.magicball.net/plugins/discourse-lba-emoji/images/takam/slight_smile.png?v=12\" title=\":slight_smile:\" class=\"emoji emoji-custom\" alt=\":slight_smile:\" loading=\"lazy\" width=\"20\" height=\"20\"></p>",
        "post_number": 2,
        "post_type": 1,
        "posts_count": 34,
        "updated_at": "2024-10-25T17:11:47.815Z",
        "reply_count": 0,
        "reply_to_post_number": 1,
        "quote_count": 0,
        "incoming_link_count": 0,
        "reads": 0,
        "readers_count": 0,
        "score": 0.0,
        "yours": false,
        "topic_id": 7911,
        "topic_slug": "is-there-a-lba-that-we-play-as-zoe",
        "display_username": null,
        "primary_group_name": null,
        "flair_name": null,
        "flair_url": null,
        "flair_bg_color": null,
        "flair_color": null,
        "flair_group_id": null,
        "badges_granted": [],
        "version": 1,
        "can_edit": false,
        "can_delete": false,
        "can_recover": false,
        "can_see_hidden_post": false,
        "can_wiki": false,
        "read": false,
        "user_title": null,
        "reply_to_user": {
          "id": 1285,
          "username": "Blafards61",
          "name": null,
          "avatar_template": "/user_avatar/forum.magicball.net/blafards61/{size}/32_2.png"
        },
        "bookmarked": false,
        "actions_summary": [
          {
            "id": 2,
            "can_act": true
          },
          {
            "id": 6,
            "can_act": true
          },
          {
            "id": 3,
            "can_act": true
          },
          {
            "id": 4,
            "can_act": true
          },
          {
            "id": 8,
            "can_act": true
          },
          {
            "id": 10,
            "can_act": true
          },
          {
            "id": 7,
            "can_act": true
          }
        ],
        "moderator": false,
        "admin": false,
        "staff": false,
        "group_moderator": true,
        "user_id": 2,
        "hidden": false,
        "trust_level": 1,
        "deleted_at": null,
        "user_deleted": false,
        "edit_reason": null,
        "can_view_edit_history": false,
        "wiki": false,
        "post_url": "/t/is-there-a-lba-that-we-play-as-zoe/7911/2",
        "reactions": [],
        "current_user_reaction": null,
        "reaction_users_count": 0,
        "current_user_used_main_reaction": false,
        "can_accept_answer": false,
        "can_unaccept_answer": false,
        "accepted_answer": false,
        "topic_accepted_answer": null
      },
      {
        "id": 205782,
        "name": null,
        "username": "xesf",
        "avatar_template": "/user_avatar/forum.magicball.net/xesf/{size}/122_2.png",
        "created_at": "2004-12-30T20:42:07.000Z",
        "cooked": "<p>Yeah, check the <a href=\"/t/lba-modifications-quick-start-modding-tools-updated-01-04-2009/6279/1\">quick start and informations</a> thread. You can easly do that job <img src=\"//forum.magicball.net/plugins/discourse-lba-emoji/images/takam/wink.png?v=12\" title=\":wink:\" class=\"emoji emoji-custom\" alt=\":wink:\" loading=\"lazy\" width=\"20\" height=\"20\"><br>\nAnyway, it could not work smothly because some Twinsen animations doesnt match with Zo body, but try and youll see <img src=\"//forum.magicball.net/plugins/discourse-lba-emoji/images/takam/slight_smile.png?v=12\" title=\":slight_smile:\" class=\"emoji emoji-custom\" alt=\":slight_smile:\" loading=\"lazy\" width=\"20\" height=\"20\"></p>\n<p>Welcome to the forum and enjoy your stay</p>",
        "post_number": 3,
        "post_type": 1,
        "posts_count": 34,
        "updated_at": "2024-10-25T19:52:01.578Z",
        "reply_count": 1,
        "reply_to_post_number": 1,
        "quote_count": 0,
        "incoming_link_count": 2,
        "reads": 0,
        "readers_count": 0,
        "score": 15.0,
        "yours": false,
        "topic_id": 7911,
        "topic_slug": "is-there-a-lba-that-we-play-as-zoe",
        "display_username": null,
        "primary_group_name": null,
        "flair_name": null,
        "flair_url": null,
        "flair_bg_color": null,
        "flair_color": null,
        "flair_group_id": null,
        "badges_granted": [],
        "version": 1,
        "can_edit": false,
        "can_delete": false,
        "can_recover": false,
        "can_see_hidden_post": false,
        "can_wiki": false,
        "link_counts": [
          {
            "url": "https://forum.magicball.net/t/lba-modifications-quick-start-modding-tools-updated-01-04-2009/6279",
            "internal": true,
            "reflection": false,
            "title": "LBA Modifications: Quick Start & Modding Tools [updated: 01-04-2009]",
            "clicks": 0
          }
        ],
        "read": false,
        "user_title": null,
        "reply_to_user": {
          "id": 1285,
          "username": "Blafards61",
          "name": null,
          "avatar_template": "/user_avatar/forum.magicball.net/blafards61/{size}/32_2.png"
        },
        "bookmarked": false,
        "actions_summary": [
          {
            "id": 2,
            "can_act": true
          },
          {
            "id": 6,
            "can_act": true
          },
          {
            "id": 3,
            "can_act": true
          },
          {
            "id": 4,
            "can_act": true
          },
          {
            "id": 8,
            "can_act": true
          },
          {
            "id": 10,
            "can_act": true
          },
          {
            "id": 7,
            "can_act": true
          }
        ],
        "moderator": false,
        "admin": false,
        "staff": false,
        "group_moderator": true,
        "user_id": 463,
        "hidden": false,
        "trust_level": 2,
        "deleted_at": null,
        "user_deleted": false,
        "edit_reason": null,
        "can_view_edit_history": false,
        "wiki": false,
        "post_url": "/t/is-there-a-lba-that-we-play-as-zoe/7911/3",
        "reactions": [],
        "current_user_reaction": null,
        "reaction_users_count": 0,
        "current_user_used_main_reaction": false,
        "can_accept_answer": false,
        "can_unaccept_answer": false,
        "accepted_answer": false,
        "topic_accepted_answer": null
      },
      {
        "id": 205787,
        "name": null,
        "username": "Blafards61",
        "avatar_template": "/user_avatar/forum.magicball.net/blafards61/{size}/32_2.png",
        "created_at": "2004-12-30T21:01:03.000Z",
        "cooked": "<p>Well,im not really good with editors.I opened BODY.HRQ and i see a list,how do i replace ?</p>",
        "post_number": 4,
        "post_type": 1,
        "posts_count": 34,
        "updated_at": "2024-10-25T17:11:48.046Z",
        "reply_count": 1,
        "reply_to_post_number": 3,
        "quote_count": 0,
        "incoming_link_count": 0,
        "reads": 0,
        "readers_count": 0,
        "score": 5.0,
        "yours": false,
        "topic_id": 7911,
        "topic_slug": "is-there-a-lba-that-we-play-as-zoe",
        "display_username": null,
        "primary_group_name": null,
        "flair_name": null,
        "flair_url": null,
        "flair_bg_color": null,
        "flair_color": null,
        "flair_group_id": null,
        "badges_granted": [],
        "version": 1,
        "can_edit": false,
        "can_delete": false,
        "can_recover": false,
        "can_see_hidden_post": false,
        "can_wiki": false,
        "read": false,
        "user_title": null,
        "reply_to_user": {
          "id": 463,
          "username": "xesf",
          "name": null,
          "avatar_template": "/user_avatar/forum.magicball.net/xesf/{size}/122_2.png"
        },
        "bookmarked": false,
        "actions_summary": [
          {
            "id": 2,
            "can_act": true
          },
          {
            "id": 6,
            "can_act": true
          },
          {
            "id": 3,
            "can_act": true
          },
          {
            "id": 4,
            "can_act": true
          },
          {
            "id": 8,
            "can_act": true
          },
          {
            "id": 10,
            "can_act": true
          },
          {
            "id": 7,
            "can_act": true
          }
        ],
        "moderator": false,
        "admin": false,
        "staff": false,
        "user_id": 1285,
        "hidden": false,
        "trust_level": 1,
        "deleted_at": null,
        "user_deleted": false,
        "edit_reason": null,
        "can_view_edit_history": false,
        "wiki": false,
        "post_url": "/t/is-there-a-lba-that-we-play-as-zoe/7911/4",
        "reactions": [],
        "current_user_reaction": null,
        "reaction_users_count": 0,
        "current_user_used_main_reaction": false,
        "can_accept_answer": false,
        "can_unaccept_answer": false,
        "accepted_answer": false,
        "topic_accepted_answer": null
      },
      {
        "id": 205790,
        "name": null,
        "username": "Blafards61",
        "avatar_template": "/user_avatar/forum.magicball.net/blafards61/{size}/32_2.png",
        "created_at": "2004-12-30T21:03:53.000Z",
        "cooked": "<p>I said anything,i found how to replace,but i dont know how to aply it.I save but when i play,im not Zoe.</p>",
        "post_number": 5,
        "post_type": 1,
        "posts_count": 34,
        "updated_at": "2024-10-25T17:11:48.156Z",
        "reply_count": 0,
        "reply_to_post_number": 4,
        "quote_count": 0,
        "incoming_link_count": 0,
        "reads": 0,
        "readers_count": 0,
        "score": 0.0,
        "yours": false,
        "topic_id": 7911,
        "topic_slug": "is-there-a-lba-that-we-play-as-zoe",
        "display_username": null,
        "primary_group_name": null,
        "flair_name": null,
        "flair_url": null,
        "flair_bg_color": null,
        "flair_color": null,
        "flair_group_id": null,
        "badges_granted": [],
        "version": 1,
        "can_edit": false,
        "can_delete": false,
        "can_recover": false,
        "can_see_hidden_post": false,
        "can_wiki": false,
        "read": false,
        "user_title": null,
        "reply_to_user": {
          "id": 1285,
          "username": "Blafards61",
          "name": null,
          "avatar_template": "/user_avatar/forum.magicball.net/blafards61/{size}/32_2.png"
        },
        "bookmarked": false,
        "actions_summary": [
          {
            "id": 2,
            "can_act": true
          },
          {
            "id": 6,
            "can_act": true
          },
          {
            "id": 3,
            "can_act": true
          },
          {
            "id": 4,
            "can_act": true
          },
          {
            "id": 8,
            "can_act": true
          },
          {
            "id": 10,
            "can_act": true
          },
          {
            "id": 7,
            "can_act": true
          }
        ],
        "moderator": false,
        "admin": false,
        "staff": false,
        "user_id": 1285,
        "hidden": false,
        "trust_level": 1,
        "deleted_at": null,
        "user_deleted": false,
        "edit_reason": null,
        "can_view_edit_history": false,
        "wiki": false,
        "post_url": "/t/is-there-a-lba-that-we-play-as-zoe/7911/5",
        "reactions": [],
        "current_user_reaction": null,
        "reaction_users_count": 0,
        "current_user_used_main_reaction": false,
        "can_accept_answer": false,
        "can_unaccept_answer": false,
        "accepted_answer": false,
        "topic_accepted_answer": null
      },
      {
        "id": 205791,
        "name": null,
        "username": "Battler",
        "avatar_template": "/user_avatar/forum.magicball.net/battler/{size}/208_2.png",
        "created_at": "2004-12-30T21:05:24.000Z",
        "cooked": "<p>Because maybe you replace the wrong Twinsen body. There are many of them (Twinsen w/o tunic, Twinsen with tunic, etc.).</p>",
        "post_number": 6,
        "post_type": 1,
        "posts_count": 34,
        "updated_at": "2024-10-25T17:11:48.189Z",
        "reply_count": 1,
        "reply_to_post_number": 1,
        "quote_count": 0,
        "incoming_link_count": 0,
        "reads": 0,
        "readers_count": 0,
        "score": 5.0,
        "yours": false,
        "topic_id": 7911,
        "topic_slug": "is-there-a-lba-that-we-play-as-zoe",
        "display_username": null,
        "primary_group_name": null,
        "flair_name": null,
        "flair_url": null,
        "flair_bg_color": null,
        "flair_color": null,
        "flair_group_id": null,
        "badges_granted": [],
        "version": 1,
        "can_edit": false,
        "can_delete": false,
        "can_recover": false,
        "can_see_hidden_post": false,
        "can_wiki": false,
        "read": false,
        "user_title": null,
        "reply_to_user": {
          "id": 1285,
          "username": "Blafards61",
          "name": null,
          "avatar_template": "/user_avatar/forum.magicball.net/blafards61/{size}/32_2.png"
        },
        "bookmarked": false,
        "actions_summary": [
          {
            "id": 2,
            "can_act": true
          },
          {
            "id": 6,
            "can_act": true
          },
          {
            "id": 3,
            "can_act": true
          },
          {
            "id": 4,
            "can_act": true
          },
          {
            "id": 8,
            "can_act": true
          },
          {
            "id": 10,
            "can_act": true
          },
          {
            "id": 7,
            "can_act": true
          }
        ],
        "moderator": false,
        "admin": false,
        "staff": false,
        "user_id": 1016,
        "hidden": false,
        "trust_level": 2,
        "deleted_at": null,
        "user_deleted": false,
        "edit_reason": null,
        "can_view_edit_history": false,
        "wiki": false,
        "post_url": "/t/is-there-a-lba-that-we-play-as-zoe/7911/6",
        "reactions": [],
        "current_user_reaction": null,
        "reaction_users_count": 0,
        "current_user_used_main_reaction": false,
        "can_accept_answer": false,
        "can_unaccept_answer": false,
        "accepted_answer": false,
        "topic_accepted_answer": null
      },
      {
        "id": 205792,
        "name": null,
        "username": "Blafards61",
        "avatar_template": "/user_avatar/forum.magicball.net/blafards61/{size}/32_2.png",
        "created_at": "2004-12-30T21:07:37.000Z",
        "cooked": "<p>I replace Twisen without tunic with Zoe by<br>\ndouble clicking Zoe and save it somewhere.<br>\nAnd i went on Twisen without Tunic and i went in Commend,replace selected entris with and I selected the saved file (Zoe).<br>\nI save my project.</p>\n<p>Now the only thing that I dont know is how to aply it.</p>",
        "post_number": 7,
        "post_type": 1,
        "posts_count": 34,
        "updated_at": "2024-10-25T17:11:48.222Z",
        "reply_count": 1,
        "reply_to_post_number": 6,
        "quote_count": 0,
        "incoming_link_count": 0,
        "reads": 0,
        "readers_count": 0,
        "score": 5.0,
        "yours": false,
        "topic_id": 7911,
        "topic_slug": "is-there-a-lba-that-we-play-as-zoe",
        "display_username": null,
        "primary_group_name": null,
        "flair_name": null,
        "flair_url": null,
        "flair_bg_color": null,
        "flair_color": null,
        "flair_group_id": null,
        "badges_granted": [],
        "version": 1,
        "can_edit": false,
        "can_delete": false,
        "can_recover": false,
        "can_see_hidden_post": false,
        "can_wiki": false,
        "read": false,
        "user_title": null,
        "reply_to_user": {
          "id": 1016,
          "username": "Battler",
          "name": null,
          "avatar_template": "/user_avatar/forum.magicball.net/battler/{size}/208_2.png"
        },
        "bookmarked": false,
        "actions_summary": [
          {
            "id": 2,
            "can_act": true
          },
          {
            "id": 6,
            "can_act": true
          },
          {
            "id": 3,
            "can_act": true
          },
          {
            "id": 4,
            "can_act": true
          },
          {
            "id": 8,
            "can_act": true
          },
          {
            "id": 10,
            "can_act": true
          },
          {
            "id": 7,
            "can_act": true
          }
        ],
        "moderator": false,
        "admin": false,
        "staff": false,
        "user_id": 1285,
        "hidden": false,
        "trust_level": 1,
        "deleted_at": null,
        "user_deleted": false,
        "edit_reason": null,
        "can_view_edit_history": false,
        "wiki": false,
        "post_url": "/t/is-there-a-lba-that-we-play-as-zoe/7911/7",
        "reactions": [],
        "current_user_reaction": null,
        "reaction_users_count": 0,
        "current_user_used_main_reaction": false,
        "can_accept_answer": false,
        "can_unaccept_answer": false,
        "accepted_answer": false,
        "topic_accepted_answer": null
      },
      {
        "id": 205794,
        "name": null,
        "username": "Blafards61",
        "avatar_template": "/user_avatar/forum.magicball.net/blafards61/{size}/32_2.png",
        "created_at": "2004-12-30T21:16:22.000Z",
        "cooked": "<p>Forgot,i found ! ITS COOOOOOOOOOL <img src=\"//forum.magicball.net/plugins/discourse-lba-emoji/images/takam/smiley.png?v=12\" title=\":smiley:\" class=\"emoji emoji-custom\" alt=\":smiley:\" loading=\"lazy\" width=\"20\" height=\"20\"></p>",
        "post_number": 8,
        "post_type": 1,
        "posts_count": 34,
        "updated_at": "2024-10-25T17:11:48.296Z",
        "reply_count": 0,
        "reply_to_post_number": 7,
        "quote_count": 0,
        "incoming_link_count": 0,
        "reads": 0,
        "readers_count": 0,
        "score": 0.0,
        "yours": false,
        "topic_id": 7911,
        "topic_slug": "is-there-a-lba-that-we-play-as-zoe",
        "display_username": null,
        "primary_group_name": null,
        "flair_name": null,
        "flair_url": null,
        "flair_bg_color": null,
        "flair_color": null,
        "flair_group_id": null,
        "badges_granted": [],
        "version": 1,
        "can_edit": false,
        "can_delete": false,
        "can_recover": false,
        "can_see_hidden_post": false,
        "can_wiki": false,
        "read": false,
        "user_title": null,
        "reply_to_user": {
          "id": 1285,
          "username": "Blafards61",
          "name": null,
          "avatar_template": "/user_avatar/forum.magicball.net/blafards61/{size}/32_2.png"
        },
        "bookmarked": false,
        "actions_summary": [
          {
            "id": 2,
            "can_act": true
          },
          {
            "id": 6,
            "can_act": true
          },
          {
            "id": 3,
            "can_act": true
          },
          {
            "id": 4,
            "can_act": true
          },
          {
            "id": 8,
            "can_act": true
          },
          {
            "id": 10,
            "can_act": true
          },
          {
            "id": 7,
            "can_act": true
          }
        ],
        "moderator": false,
        "admin": false,
        "staff": false,
        "user_id": 1285,
        "hidden": false,
        "trust_level": 1,
        "deleted_at": null,
        "user_deleted": false,
        "edit_reason": null,
        "can_view_edit_history": false,
        "wiki": false,
        "post_url": "/t/is-there-a-lba-that-we-play-as-zoe/7911/8",
        "reactions": [],
        "current_user_reaction": null,
        "reaction_users_count": 0,
        "current_user_used_main_reaction": false,
        "can_accept_answer": false,
        "can_unaccept_answer": false,
        "accepted_answer": false,
        "topic_accepted_answer": null
      },
      {
        "id": 205796,
        "name": null,
        "username": "Kitarii",
        "avatar_template": "/user_avatar/forum.magicball.net/kitarii/{size}/217_2.png",
        "created_at": "2004-12-30T21:24:13.000Z",
        "cooked": "<p>she move like a bit of a spaz though, dont ya think?</p>",
        "post_number": 9,
        "post_type": 1,
        "posts_count": 34,
        "updated_at": "2024-10-25T17:11:48.364Z",
        "reply_count": 1,
        "reply_to_post_number": 1,
        "quote_count": 0,
        "incoming_link_count": 0,
        "reads": 0,
        "readers_count": 0,
        "score": 5.0,
        "yours": false,
        "topic_id": 7911,
        "topic_slug": "is-there-a-lba-that-we-play-as-zoe",
        "display_username": null,
        "primary_group_name": null,
        "flair_name": null,
        "flair_url": null,
        "flair_bg_color": null,
        "flair_color": null,
        "flair_group_id": null,
        "badges_granted": [],
        "version": 1,
        "can_edit": false,
        "can_delete": false,
        "can_recover": false,
        "can_see_hidden_post": false,
        "can_wiki": false,
        "read": false,
        "user_title": null,
        "reply_to_user": {
          "id": 1285,
          "username": "Blafards61",
          "name": null,
          "avatar_template": "/user_avatar/forum.magicball.net/blafards61/{size}/32_2.png"
        },
        "bookmarked": false,
        "actions_summary": [
          {
            "id": 2,
            "can_act": true
          },
          {
            "id": 6,
            "can_act": true
          },
          {
            "id": 3,
            "can_act": true
          },
          {
            "id": 4,
            "can_act": true
          },
          {
            "id": 8,
            "can_act": true
          },
          {
            "id": 10,
            "can_act": true
          },
          {
            "id": 7,
            "can_act": true
          }
        ],
        "moderator": true,
        "admin": false,
        "staff": true,
        "user_id": 1079,
        "hidden": false,
        "trust_level": 1,
        "deleted_at": null,
        "user_deleted": false,
        "edit_reason": null,
        "can_view_edit_history": false,
        "wiki": false,
        "post_url": "/t/is-there-a-lba-that-we-play-as-zoe/7911/9",
        "reactions": [],
        "current_user_reaction": null,
        "reaction_users_count": 0,
        "current_user_used_main_reaction": false,
        "can_accept_answer": false,
        "can_unaccept_answer": false,
        "accepted_answer": false,
        "topic_accepted_answer": null
      },
      {
        "id": 205797,
        "name": null,
        "username": "Blafards61",
        "avatar_template": "/user_avatar/forum.magicball.net/blafards61/{size}/32_2.png",
        "created_at": "2004-12-30T21:29:33.000Z",
        "cooked": "<p>Thats what make me laught a lot.If only it wasnt of the animationit could be cool.</p>",
        "post_number": 10,
        "post_type": 1,
        "posts_count": 34,
        "updated_at": "2024-10-25T17:11:48.405Z",
        "reply_count": 0,
        "reply_to_post_number": 9,
        "quote_count": 0,
        "incoming_link_count": 0,
        "reads": 0,
        "readers_count": 0,
        "score": 0.0,
        "yours": false,
        "topic_id": 7911,
        "topic_slug": "is-there-a-lba-that-we-play-as-zoe",
        "display_username": null,
        "primary_group_name": null,
        "flair_name": null,
        "flair_url": null,
        "flair_bg_color": null,
        "flair_color": null,
        "flair_group_id": null,
        "badges_granted": [],
        "version": 1,
        "can_edit": false,
        "can_delete": false,
        "can_recover": false,
        "can_see_hidden_post": false,
        "can_wiki": false,
        "read": false,
        "user_title": null,
        "reply_to_user": {
          "id": 1079,
          "username": "Kitarii",
          "name": null,
          "avatar_template": "/user_avatar/forum.magicball.net/kitarii/{size}/217_2.png"
        },
        "bookmarked": false,
        "actions_summary": [
          {
            "id": 2,
            "can_act": true
          },
          {
            "id": 6,
            "can_act": true
          },
          {
            "id": 3,
            "can_act": true
          },
          {
            "id": 4,
            "can_act": true
          },
          {
            "id": 8,
            "can_act": true
          },
          {
            "id": 10,
            "can_act": true
          },
          {
            "id": 7,
            "can_act": true
          }
        ],
        "moderator": false,
        "admin": false,
        "staff": false,
        "user_id": 1285,
        "hidden": false,
        "trust_level": 1,
        "deleted_at": null,
        "user_deleted": false,
        "edit_reason": null,
        "can_view_edit_history": false,
        "wiki": false,
        "post_url": "/t/is-there-a-lba-that-we-play-as-zoe/7911/10",
        "reactions": [],
        "current_user_reaction": null,
        "reaction_users_count": 0,
        "current_user_used_main_reaction": false,
        "can_accept_answer": false,
        "can_unaccept_answer": false,
        "accepted_answer": false,
        "topic_accepted_answer": null
      },
      {
        "id": 205800,
        "name": null,
        "username": "Kitarii",
        "avatar_template": "/user_avatar/forum.magicball.net/kitarii/{size}/217_2.png",
        "created_at": "2004-12-30T22:00:27.000Z",
        "cooked": "<p>i dont know much about this, but i seem to remember someone telling me you can swap the animations around</p>",
        "post_number": 11,
        "post_type": 1,
        "posts_count": 34,
        "updated_at": "2024-10-25T17:11:48.509Z",
        "reply_count": 1,
        "reply_to_post_number": 1,
        "quote_count": 0,
        "incoming_link_count": 0,
        "reads": 0,
        "readers_count": 0,
        "score": 5.0,
        "yours": false,
        "topic_id": 7911,
        "topic_slug": "is-there-a-lba-that-we-play-as-zoe",
        "display_username": null,
        "primary_group_name": null,
        "flair_name": null,
        "flair_url": null,
        "flair_bg_color": null,
        "flair_color": null,
        "flair_group_id": null,
        "badges_granted": [],
        "version": 1,
        "can_edit": false,
        "can_delete": false,
        "can_recover": false,
        "can_see_hidden_post": false,
        "can_wiki": false,
        "read": false,
        "user_title": null,
        "reply_to_user": {
          "id": 1285,
          "username": "Blafards61",
          "name": null,
          "avatar_template": "/user_avatar/forum.magicball.net/blafards61/{size}/32_2.png"
        },
        "bookmarked": false,
        "actions_summary": [
          {
            "id": 2,
            "can_act": true
          },
          {
            "id": 6,
            "can_act": true
          },
          {
            "id": 3,
            "can_act": true
          },
          {
            "id": 4,
            "can_act": true
          },
          {
            "id": 8,
            "can_act": true
          },
          {
            "id": 10,
            "can_act": true
          },
          {
            "id": 7,
            "can_act": true
          }
        ],
        "moderator": true,
        "admin": false,
        "staff": true,
        "user_id": 1079,
        "hidden": false,
        "trust_level": 1,
        "deleted_at": null,
        "user_deleted": false,
        "edit_reason": null,
        "can_view_edit_history": false,
        "wiki": false,
        "post_url": "/t/is-there-a-lba-that-we-play-as-zoe/7911/11",
        "reactions": [],
        "current_user_reaction": null,
        "reaction_users_count": 0,
        "current_user_used_main_reaction": false,
        "can_accept_answer": false,
        "can_unaccept_answer": false,
        "accepted_answer": false,
        "topic_accepted_answer": null
      },
      {
        "id": 205801,
        "name": null,
        "username": "Blafards61",
        "avatar_template": "/user_avatar/forum.magicball.net/blafards61/{size}/32_2.png",
        "created_at": "2004-12-30T22:02:12.000Z",
        "cooked": "<p>Anyway.Ill post a thread later.<br>\nNow i have a little problem.I replaced Zoe by Twisen and Zoe with Umbrella by Twisen with Tunic,but i dont work.I see Zoe as Zoeis that normal?</p>",
        "post_number": 12,
        "post_type": 1,
        "posts_count": 34,
        "updated_at": "2024-10-25T17:11:48.544Z",
        "reply_count": 2,
        "reply_to_post_number": 11,
        "quote_count": 0,
        "incoming_link_count": 0,
        "reads": 0,
        "readers_count": 0,
        "score": 10.0,
        "yours": false,
        "topic_id": 7911,
        "topic_slug": "is-there-a-lba-that-we-play-as-zoe",
        "display_username": null,
        "primary_group_name": null,
        "flair_name": null,
        "flair_url": null,
        "flair_bg_color": null,
        "flair_color": null,
        "flair_group_id": null,
        "badges_granted": [],
        "version": 1,
        "can_edit": false,
        "can_delete": false,
        "can_recover": false,
        "can_see_hidden_post": false,
        "can_wiki": false,
        "read": false,
        "user_title": null,
        "reply_to_user": {
          "id": 1079,
          "username": "Kitarii",
          "name": null,
          "avatar_template": "/user_avatar/forum.magicball.net/kitarii/{size}/217_2.png"
        },
        "bookmarked": false,
        "actions_summary": [
          {
            "id": 2,
            "can_act": true
          },
          {
            "id": 6,
            "can_act": true
          },
          {
            "id": 3,
            "can_act": true
          },
          {
            "id": 4,
            "can_act": true
          },
          {
            "id": 8,
            "can_act": true
          },
          {
            "id": 10,
            "can_act": true
          },
          {
            "id": 7,
            "can_act": true
          }
        ],
        "moderator": false,
        "admin": false,
        "staff": false,
        "user_id": 1285,
        "hidden": false,
        "trust_level": 1,
        "deleted_at": null,
        "user_deleted": false,
        "edit_reason": null,
        "can_view_edit_history": false,
        "wiki": false,
        "post_url": "/t/is-there-a-lba-that-we-play-as-zoe/7911/12",
        "reactions": [],
        "current_user_reaction": null,
        "reaction_users_count": 0,
        "current_user_used_main_reaction": false,
        "can_accept_answer": false,
        "can_unaccept_answer": false,
        "accepted_answer": false,
        "topic_accepted_answer": null
      },
      {
        "id": 205802,
        "name": null,
        "username": "Blafards61",
        "avatar_template": "/user_avatar/forum.magicball.net/blafards61/{size}/32_2.png",
        "created_at": "2004-12-30T22:03:23.000Z",
        "cooked": "<p>I forgot to say that I opened ANIM.HQR but,I only see Twinsens animation,I cant exchange.</p>",
        "post_number": 13,
        "post_type": 1,
        "posts_count": 34,
        "updated_at": "2024-10-25T17:11:48.576Z",
        "reply_count": 0,
        "reply_to_post_number": 12,
        "quote_count": 0,
        "incoming_link_count": 0,
        "reads": 0,
        "readers_count": 0,
        "score": 0.0,
        "yours": false,
        "topic_id": 7911,
        "topic_slug": "is-there-a-lba-that-we-play-as-zoe",
        "display_username": null,
        "primary_group_name": null,
        "flair_name": null,
        "flair_url": null,
        "flair_bg_color": null,
        "flair_color": null,
        "flair_group_id": null,
        "badges_granted": [],
        "version": 1,
        "can_edit": false,
        "can_delete": false,
        "can_recover": false,
        "can_see_hidden_post": false,
        "can_wiki": false,
        "read": false,
        "user_title": null,
        "reply_to_user": {
          "id": 1285,
          "username": "Blafards61",
          "name": null,
          "avatar_template": "/user_avatar/forum.magicball.net/blafards61/{size}/32_2.png"
        },
        "bookmarked": false,
        "actions_summary": [
          {
            "id": 2,
            "can_act": true
          },
          {
            "id": 6,
            "can_act": true
          },
          {
            "id": 3,
            "can_act": true
          },
          {
            "id": 4,
            "can_act": true
          },
          {
            "id": 8,
            "can_act": true
          },
          {
            "id": 10,
            "can_act": true
          },
          {
            "id": 7,
            "can_act": true
          }
        ],
        "moderator": false,
        "admin": false,
        "staff": false,
        "user_id": 1285,
        "hidden": false,
        "trust_level": 1,
        "deleted_at": null,
        "user_deleted": false,
        "edit_reason": null,
        "can_view_edit_history": false,
        "wiki": false,
        "post_url": "/t/is-there-a-lba-that-we-play-as-zoe/7911/13",
        "reactions": [],
        "current_user_reaction": null,
        "reaction_users_count": 0,
        "current_user_used_main_reaction": false,
        "can_accept_answer": false,
        "can_unaccept_answer": false,
        "accepted_answer": false,
        "topic_accepted_answer": null
      },
      {
        "id": 205803,
        "name": null,
        "username": "Kitarii",
        "avatar_template": "/user_avatar/forum.magicball.net/kitarii/{size}/217_2.png",
        "created_at": "2004-12-30T22:05:00.000Z",
        "cooked": "<aside class=\"quote no-group\" data-username=\"Blafards61\">\n<div class=\"title\">\n<div class=\"quote-controls\"></div>\n<img loading=\"lazy\" alt=\"\" width=\"24\" height=\"24\" src=\"//forum.magicball.net/user_avatar/localhost/blafards61/48/32_2.png\" class=\"avatar\"> Blafards61:</div>\n<blockquote>\n<p>Anyway.Ill post a thread later.<br>\nNow i have a little problem.I replaced Zoe by Twisen and Zoe with Umbrella by Twisen with Tunic,but i dont work.I see Zoe as Zoeis that normal?</p>\n</blockquote>\n</aside>\n<p>you need to put twinsen in place of zoe as well</p>",
        "post_number": 14,
        "post_type": 1,
        "posts_count": 34,
        "updated_at": "2024-10-25T17:11:48.608Z",
        "reply_count": 1,
        "reply_to_post_number": 12,
        "quote_count": 0,
        "incoming_link_count": 0,
        "reads": 0,
        "readers_count": 0,
        "score": 5.0,
        "yours": false,
        "topic_id": 7911,
        "topic_slug": "is-there-a-lba-that-we-play-as-zoe",
        "display_username": null,
        "primary_group_name": null,
        "flair_name": null,
        "flair_url": null,
        "flair_bg_color": null,
        "flair_color": null,
        "flair_group_id": null,
        "badges_granted": [],
        "version": 1,
        "can_edit": false,
        "can_delete": false,
        "can_recover": false,
        "can_see_hidden_post": false,
        "can_wiki": false,
        "read": false,
        "user_title": null,
        "reply_to_user": {
          "id": 1285,
          "username": "Blafards61",
          "name": null,
          "avatar_template": "/user_avatar/forum.magicball.net/blafards61/{size}/32_2.png"
        },
        "bookmarked": false,
        "actions_summary": [
          {
            "id": 2,
            "can_act": true
          },
          {
            "id": 6,
            "can_act": true
          },
          {
            "id": 3,
            "can_act": true
          },
          {
            "id": 4,
            "can_act": true
          },
          {
            "id": 8,
            "can_act": true
          },
          {
            "id": 10,
            "can_act": true
          },
          {
            "id": 7,
            "can_act": true
          }
        ],
        "moderator": true,
        "admin": false,
        "staff": true,
        "user_id": 1079,
        "hidden": false,
        "trust_level": 1,
        "deleted_at": null,
        "user_deleted": false,
        "edit_reason": null,
        "can_view_edit_history": false,
        "wiki": false,
        "post_url": "/t/is-there-a-lba-that-we-play-as-zoe/7911/14",
        "reactions": [],
        "current_user_reaction": null,
        "reaction_users_count": 0,
        "current_user_used_main_reaction": false,
        "can_accept_answer": false,
        "can_unaccept_answer": false,
        "accepted_answer": false,
        "topic_accepted_answer": null
      },
      {
        "id": 205806,
        "name": null,
        "username": "Blafards61",
        "avatar_template": "/user_avatar/forum.magicball.net/blafards61/{size}/32_2.png",
        "created_at": "2004-12-30T22:15:01.000Z",
        "cooked": "<aside class=\"quote no-group\">\n<blockquote>\n<p>you need to put twinsen in place of zoe as well</p>\n</blockquote>\n</aside>\n<p>What do you mean by that?</p>",
        "post_number": 15,
        "post_type": 1,
        "posts_count": 34,
        "updated_at": "2024-10-25T17:11:48.716Z",
        "reply_count": 1,
        "reply_to_post_number": 14,
        "quote_count": 0,
        "incoming_link_count": 0,
        "reads": 0,
        "readers_count": 0,
        "score": 5.0,
        "yours": false,
        "topic_id": 7911,
        "topic_slug": "is-there-a-lba-that-we-play-as-zoe",
        "display_username": null,
        "primary_group_name": null,
        "flair_name": null,
        "flair_url": null,
        "flair_bg_color": null,
        "flair_color": null,
        "flair_group_id": null,
        "badges_granted": [],
        "version": 1,
        "can_edit": false,
        "can_delete": false,
        "can_recover": false,
        "can_see_hidden_post": false,
        "can_wiki": false,
        "read": false,
        "user_title": null,
        "reply_to_user": {
          "id": 1079,
          "username": "Kitarii",
          "name": null,
          "avatar_template": "/user_avatar/forum.magicball.net/kitarii/{size}/217_2.png"
        },
        "bookmarked": false,
        "actions_summary": [
          {
            "id": 2,
            "can_act": true
          },
          {
            "id": 6,
            "can_act": true
          },
          {
            "id": 3,
            "can_act": true
          },
          {
            "id": 4,
            "can_act": true
          },
          {
            "id": 8,
            "can_act": true
          },
          {
            "id": 10,
            "can_act": true
          },
          {
            "id": 7,
            "can_act": true
          }
        ],
        "moderator": false,
        "admin": false,
        "staff": false,
        "user_id": 1285,
        "hidden": false,
        "trust_level": 1,
        "deleted_at": null,
        "user_deleted": false,
        "edit_reason": null,
        "can_view_edit_history": false,
        "wiki": false,
        "post_url": "/t/is-there-a-lba-that-we-play-as-zoe/7911/15",
        "reactions": [],
        "current_user_reaction": null,
        "reaction_users_count": 0,
        "current_user_used_main_reaction": false,
        "can_accept_answer": false,
        "can_unaccept_answer": false,
        "accepted_answer": false,
        "topic_accepted_answer": null
      },
      {
        "id": 205812,
        "name": null,
        "username": "Golemboy",
        "avatar_template": "/user_avatar/forum.magicball.net/golemboy/{size}/191_2.png",
        "created_at": "2004-12-30T23:06:15.000Z",
        "cooked": "<p>there are many many zoe bodies, they are not all grouped together. there are some things in the game that seem to be strangely un-changable, like the car outside of your house. what is the deal with that damn car! no matter what i change the body entry to, its still the sam. always! mutter mutter kill mutter mutter car mutter mutter</p>\n<p>anyway, yeah. you can make zoe move better by changing the animations, they are there, but there wont be one of say, zoe throwing darts, zoe running etc as they are not used in the game. lba1 would be better, because of the fighting zoe clone. your problem is almost certainly that you havnt found ALL of the zoe bodies and replaced them, or that you forgot to build the file (i do that alot:D)</p>\n<p>my advice if you want to do a full mod, is that it is tedious. and boring. and sometimes you will go crazy because packed wont do quite the thing you want it to. this is why i gave up on Its a Clones Life, at least until the kinks in SceneManager are worked out (or Scene Editor, depending on who gets the life scripts worked out in a working version first :D). Then I shall come back wreaking a great vengance on my enemies, raining fire an such.</p>\n<p>btw download and try out LBArchitect. you can alter and design new maps! the iscometric bricks are tricky at first, buut once you get the hang of it, things really can look very cool</p>",
        "post_number": 16,
        "post_type": 1,
        "posts_count": 34,
        "updated_at": "2024-10-25T17:11:48.928Z",
        "reply_count": 1,
        "reply_to_post_number": 15,
        "quote_count": 0,
        "incoming_link_count": 0,
        "reads": 0,
        "readers_count": 0,
        "score": 5.0,
        "yours": false,
        "topic_id": 7911,
        "topic_slug": "is-there-a-lba-that-we-play-as-zoe",
        "display_username": null,
        "primary_group_name": null,
        "flair_name": null,
        "flair_url": null,
        "flair_bg_color": null,
        "flair_color": null,
        "flair_group_id": null,
        "badges_granted": [],
        "version": 1,
        "can_edit": false,
        "can_delete": false,
        "can_recover": false,
        "can_see_hidden_post": false,
        "can_wiki": false,
        "read": false,
        "user_title": null,
        "reply_to_user": {
          "id": 1285,
          "username": "Blafards61",
          "name": null,
          "avatar_template": "/user_avatar/forum.magicball.net/blafards61/{size}/32_2.png"
        },
        "bookmarked": false,
        "actions_summary": [
          {
            "id": 2,
            "can_act": true
          },
          {
            "id": 6,
            "can_act": true
          },
          {
            "id": 3,
            "can_act": true
          },
          {
            "id": 4,
            "can_act": true
          },
          {
            "id": 8,
            "can_act": true
          },
          {
            "id": 10,
            "can_act": true
          },
          {
            "id": 7,
            "can_act": true
          }
        ],
        "moderator": false,
        "admin": false,
        "staff": false,
        "user_id": 874,
        "hidden": false,
        "trust_level": 1,
        "deleted_at": null,
        "user_deleted": false,
        "edit_reason": null,
        "can_view_edit_history": false,
        "wiki": false,
        "post_url": "/t/is-there-a-lba-that-we-play-as-zoe/7911/16",
        "reactions": [],
        "current_user_reaction": null,
        "reaction_users_count": 0,
        "current_user_used_main_reaction": false,
        "can_accept_answer": false,
        "can_unaccept_answer": false,
        "accepted_answer": false,
        "topic_accepted_answer": null
      },
      {
        "id": 205813,
        "name": null,
        "username": "Blafards61",
        "avatar_template": "/user_avatar/forum.magicball.net/blafards61/{size}/32_2.png",
        "created_at": "2004-12-30T23:10:11.000Z",
        "cooked": "<p>Well,when I open ANIM.HQR (LBA2),I only see Twinsens animations,not other Characters one.Only on LBA1 that we can see all.Well,if someone can make the animation for me,It will be great (LBA2)</p>",
        "post_number": 17,
        "post_type": 1,
        "posts_count": 34,
        "updated_at": "2024-10-25T17:11:48.979Z",
        "reply_count": 1,
        "reply_to_post_number": 16,
        "quote_count": 0,
        "incoming_link_count": 0,
        "reads": 0,
        "readers_count": 0,
        "score": 5.0,
        "yours": false,
        "topic_id": 7911,
        "topic_slug": "is-there-a-lba-that-we-play-as-zoe",
        "display_username": null,
        "primary_group_name": null,
        "flair_name": null,
        "flair_url": null,
        "flair_bg_color": null,
        "flair_color": null,
        "flair_group_id": null,
        "badges_granted": [],
        "version": 1,
        "can_edit": false,
        "can_delete": false,
        "can_recover": false,
        "can_see_hidden_post": false,
        "can_wiki": false,
        "read": false,
        "user_title": null,
        "reply_to_user": {
          "id": 874,
          "username": "Golemboy",
          "name": null,
          "avatar_template": "/user_avatar/forum.magicball.net/golemboy/{size}/191_2.png"
        },
        "bookmarked": false,
        "actions_summary": [
          {
            "id": 2,
            "can_act": true
          },
          {
            "id": 6,
            "can_act": true
          },
          {
            "id": 3,
            "can_act": true
          },
          {
            "id": 4,
            "can_act": true
          },
          {
            "id": 8,
            "can_act": true
          },
          {
            "id": 10,
            "can_act": true
          },
          {
            "id": 7,
            "can_act": true
          }
        ],
        "moderator": false,
        "admin": false,
        "staff": false,
        "user_id": 1285,
        "hidden": false,
        "trust_level": 1,
        "deleted_at": null,
        "user_deleted": false,
        "edit_reason": null,
        "can_view_edit_history": false,
        "wiki": false,
        "post_url": "/t/is-there-a-lba-that-we-play-as-zoe/7911/17",
        "reactions": [],
        "current_user_reaction": null,
        "reaction_users_count": 0,
        "current_user_used_main_reaction": false,
        "can_accept_answer": false,
        "can_unaccept_answer": false,
        "accepted_answer": false,
        "topic_accepted_answer": null
      },
      {
        "id": 205815,
        "name": null,
        "username": "Golemboy",
        "avatar_template": "/user_avatar/forum.magicball.net/golemboy/{size}/191_2.png",
        "created_at": "2004-12-30T23:13:05.000Z",
        "cooked": "<p>woah, that post i just wrote is so long that it got rplied before i was finished. spooky</p>\n<p>blafard, if not sure whats going on with that. does your lba2 function properly? if so then i dont know. can you take a screen shot (with the prnt scrn button) and show us? otherwise i dont know whats wrong. is the file info for lba2 anims finished?</p>",
        "post_number": 18,
        "post_type": 1,
        "posts_count": 34,
        "updated_at": "2024-10-25T17:11:49.053Z",
        "reply_count": 1,
        "reply_to_post_number": 17,
        "quote_count": 0,
        "incoming_link_count": 0,
        "reads": 0,
        "readers_count": 0,
        "score": 5.0,
        "yours": false,
        "topic_id": 7911,
        "topic_slug": "is-there-a-lba-that-we-play-as-zoe",
        "display_username": null,
        "primary_group_name": null,
        "flair_name": null,
        "flair_url": null,
        "flair_bg_color": null,
        "flair_color": null,
        "flair_group_id": null,
        "badges_granted": [],
        "version": 1,
        "can_edit": false,
        "can_delete": false,
        "can_recover": false,
        "can_see_hidden_post": false,
        "can_wiki": false,
        "read": false,
        "user_title": null,
        "reply_to_user": {
          "id": 1285,
          "username": "Blafards61",
          "name": null,
          "avatar_template": "/user_avatar/forum.magicball.net/blafards61/{size}/32_2.png"
        },
        "bookmarked": false,
        "actions_summary": [
          {
            "id": 2,
            "can_act": true
          },
          {
            "id": 6,
            "can_act": true
          },
          {
            "id": 3,
            "can_act": true
          },
          {
            "id": 4,
            "can_act": true
          },
          {
            "id": 8,
            "can_act": true
          },
          {
            "id": 10,
            "can_act": true
          },
          {
            "id": 7,
            "can_act": true
          }
        ],
        "moderator": false,
        "admin": false,
        "staff": false,
        "user_id": 874,
        "hidden": false,
        "trust_level": 1,
        "deleted_at": null,
        "user_deleted": false,
        "edit_reason": null,
        "can_view_edit_history": false,
        "wiki": false,
        "post_url": "/t/is-there-a-lba-that-we-play-as-zoe/7911/18",
        "reactions": [],
        "current_user_reaction": null,
        "reaction_users_count": 0,
        "current_user_used_main_reaction": false,
        "can_accept_answer": false,
        "can_unaccept_answer": false,
        "accepted_answer": false,
        "topic_accepted_answer": null
      },
      {
        "id": 205818,
        "name": null,
        "username": "Blafards61",
        "avatar_template": "/user_avatar/forum.magicball.net/blafards61/{size}/32_2.png",
        "created_at": "2004-12-30T23:19:36.000Z",
        "cooked": "<p><span alt=\"\" role=\"presentation\" class=\"broken-image\" title=\"This image is broken\"><svg class=\"fa d-icon d-icon-unlink svg-icon\" aria-hidden=\"true\"><use href=\"#unlink\"></use></svg></span><br>\nThats showing that Im really in LBA2 folder and Choosing ANIM.HQR</p>\n<p><span alt=\"\" role=\"presentation\" class=\"broken-image\" title=\"This image is broken\"><svg class=\"fa d-icon d-icon-unlink svg-icon\" aria-hidden=\"true\"><use href=\"#unlink\"></use></svg></span><br>\nThats showing the end of my list with Twisens animation</p>\n<p>And thats strange,because on <a href=\"http://chaosfish.free.fr/lbafileinfo/\" class=\"inline-onebox\" rel=\"noopener nofollow ugc\">Little Big Adventure File Information</a><br>\nthere is no ANIM.HQR section in LBA,HQR.</p>\n<p>And YES,my LBA 2 is working REALLY good,all the character have their animations.</p>",
        "post_number": 19,
        "post_type": 1,
        "posts_count": 34,
        "updated_at": "2024-10-25T17:11:49.159Z",
        "reply_count": 1,
        "reply_to_post_number": 18,
        "quote_count": 0,
        "incoming_link_count": 0,
        "reads": 0,
        "readers_count": 0,
        "score": 5.0,
        "yours": false,
        "topic_id": 7911,
        "topic_slug": "is-there-a-lba-that-we-play-as-zoe",
        "display_username": null,
        "primary_group_name": null,
        "flair_name": null,
        "flair_url": null,
        "flair_bg_color": null,
        "flair_color": null,
        "flair_group_id": null,
        "badges_granted": [],
        "version": 1,
        "can_edit": false,
        "can_delete": false,
        "can_recover": false,
        "can_see_hidden_post": false,
        "can_wiki": false,
        "link_counts": [
          {
            "url": "http://chaosfish.free.fr/lbafileinfo/",
            "internal": false,
            "reflection": false,
            "title": "Little Big Adventure File Information",
            "clicks": 0
          }
        ],
        "read": false,
        "user_title": null,
        "reply_to_user": {
          "id": 874,
          "username": "Golemboy",
          "name": null,
          "avatar_template": "/user_avatar/forum.magicball.net/golemboy/{size}/191_2.png"
        },
        "bookmarked": false,
        "actions_summary": [
          {
            "id": 2,
            "can_act": true
          },
          {
            "id": 6,
            "can_act": true
          },
          {
            "id": 3,
            "can_act": true
          },
          {
            "id": 4,
            "can_act": true
          },
          {
            "id": 8,
            "can_act": true
          },
          {
            "id": 10,
            "can_act": true
          },
          {
            "id": 7,
            "can_act": true
          }
        ],
        "moderator": false,
        "admin": false,
        "staff": false,
        "user_id": 1285,
        "hidden": false,
        "trust_level": 1,
        "deleted_at": null,
        "user_deleted": false,
        "edit_reason": null,
        "can_view_edit_history": false,
        "wiki": false,
        "post_url": "/t/is-there-a-lba-that-we-play-as-zoe/7911/19",
        "reactions": [],
        "current_user_reaction": null,
        "reaction_users_count": 0,
        "current_user_used_main_reaction": false,
        "can_accept_answer": false,
        "can_unaccept_answer": false,
        "accepted_answer": false,
        "topic_accepted_answer": null
      },
      {
        "id": 205820,
        "name": null,
        "username": "Golemboy",
        "avatar_template": "/user_avatar/forum.magicball.net/golemboy/{size}/191_2.png",
        "created_at": "2004-12-30T23:23:40.000Z",
        "cooked": "<p>yeah, i just checked mine and the problem is that the lba2 anim.hqr, being giganormous, has not been fully documented. therefore packEd cannot tell you which is which. i suggest that if you really want to do this mod you do it with lba1 which has fully listed anims and just about everything else, and all the maps can be modded</p>",
        "post_number": 20,
        "post_type": 1,
        "posts_count": 34,
        "updated_at": "2024-10-25T17:11:49.233Z",
        "reply_count": 0,
        "reply_to_post_number": 19,
        "quote_count": 0,
        "incoming_link_count": 0,
        "reads": 0,
        "readers_count": 0,
        "score": 0.0,
        "yours": false,
        "topic_id": 7911,
        "topic_slug": "is-there-a-lba-that-we-play-as-zoe",
        "display_username": null,
        "primary_group_name": null,
        "flair_name": null,
        "flair_url": null,
        "flair_bg_color": null,
        "flair_color": null,
        "flair_group_id": null,
        "badges_granted": [],
        "version": 1,
        "can_edit": false,
        "can_delete": false,
        "can_recover": false,
        "can_see_hidden_post": false,
        "can_wiki": false,
        "read": false,
        "user_title": null,
        "reply_to_user": {
          "id": 1285,
          "username": "Blafards61",
          "name": null,
          "avatar_template": "/user_avatar/forum.magicball.net/blafards61/{size}/32_2.png"
        },
        "bookmarked": false,
        "actions_summary": [
          {
            "id": 2,
            "can_act": true
          },
          {
            "id": 6,
            "can_act": true
          },
          {
            "id": 3,
            "can_act": true
          },
          {
            "id": 4,
            "can_act": true
          },
          {
            "id": 8,
            "can_act": true
          },
          {
            "id": 10,
            "can_act": true
          },
          {
            "id": 7,
            "can_act": true
          }
        ],
        "moderator": false,
        "admin": false,
        "staff": false,
        "user_id": 874,
        "hidden": false,
        "trust_level": 1,
        "deleted_at": null,
        "user_deleted": false,
        "edit_reason": null,
        "can_view_edit_history": false,
        "wiki": false,
        "post_url": "/t/is-there-a-lba-that-we-play-as-zoe/7911/20",
        "reactions": [],
        "current_user_reaction": null,
        "reaction_users_count": 0,
        "current_user_used_main_reaction": false,
        "can_accept_answer": false,
        "can_unaccept_answer": false,
        "accepted_answer": false,
        "topic_accepted_answer": null
      }
    ],
    "stream": [
      7914,
      205781,
      205782,
      205787,
      205790,
      205791,
      205792,
      205794,
      205796,
      205797,
      205800,
      205801,
      205802,
      205803,
      205806,
      205812,
      205813,
      205815,
      205818,
      205820,
      205823,
      205824,
      205825,
      205828,
      205837,
      205840,
      205844,
      205845,
      205851,
      205870,
      205877,
      205977,
      205979,
      205998
    ]
  },
  "timeline_lookup": [
    [
      1,
      7714
    ],
    [
      30,
      7713
    ]
  ],
  "tags_descriptions": {},
  "fancy_title": "Is there a LBA that we play as Zoe?",
  "id": 7911,
  "title": "Is there a LBA that we play as Zoe?",
  "posts_count": 34,
  "created_at": "2004-12-30T20:36:59.000Z",
  "views": 4364,
  "reply_count": 33,
  "like_count": 0,
  "last_posted_at": "2005-01-01T00:23:18.000Z",
  "visible": true,
  "closed": false,
  "archived": false,
  "has_summary": false,
  "archetype": "regular",
  "slug": "is-there-a-lba-that-we-play-as-zoe",
  "category_id": 50,
  "word_count": 52,
  "deleted_at": null,
  "user_id": 1285,
  "featured_link": null,
  "pinned_globally": false,
  "pinned_at": null,
  "pinned_until": null,
  "image_url": null,
  "slow_mode_seconds": 0,
  "draft": null,
  "draft_key": "topic_7911",
  "draft_sequence": 0,
  "unpinned": null,
  "pinned": false,
  "current_post_number": 1,
  "highest_post_number": 34,
  "deleted_by": null,
  "actions_summary": [
    {
      "id": 4,
      "count": 0,
      "hidden": false,
      "can_act": true
    },
    {
      "id": 8,
      "count": 0,
      "hidden": false,
      "can_act": true
    },
    {
      "id": 10,
      "count": 0,
      "hidden": false,
      "can_act": true
    },
    {
      "id": 7,
      "count": 0,
      "hidden": false,
      "can_act": true
    }
  ],
  "chunk_size": 20,
  "bookmarked": false,
  "topic_timer": null,
  "message_bus_last_id": 0,
  "participant_count": 6,
  "show_read_indicator": false,
  "thumbnails": null,
  "slow_mode_enabled_until": null,
  "valid_reactions": [
    "heart",
    "+1",
    "laughing",
    "open_mouth",
    "clap",
    "smiling_face_with_sunglasses",
    "confetti_ball",
    "hugs"
  ],
  "can_vote": false,
  "vote_count": 0,
  "user_voted": false,
  "discourse_zendesk_plugin_zendesk_id": null,
  "discourse_zendesk_plugin_zendesk_url": "https://your-url.zendesk.com/agent/tickets/",
  "details": {
    "can_edit": false,
    "notification_level": 1,
    "can_invite_to": true,
    "can_create_post": true,
    "can_reply_as_new_topic": true,
    "can_flag_topic": true,
    "participants": [
      {
        "id": 1285,
        "username": "Blafards61",
        "name": null,
        "avatar_template": "/user_avatar/forum.magicball.net/blafards61/{size}/32_2.png",
        "post_count": 15,
        "primary_group_name": null,
        "flair_name": null,
        "flair_url": null,
        "flair_color": null,
        "flair_bg_color": null,
        "flair_group_id": null,
        "trust_level": 1
      },
      {
        "id": 1016,
        "username": "Battler",
        "name": null,
        "avatar_template": "/user_avatar/forum.magicball.net/battler/{size}/208_2.png",
        "post_count": 6,
        "primary_group_name": null,
        "flair_name": null,
        "flair_url": null,
        "flair_color": null,
        "flair_bg_color": null,
        "flair_group_id": null,
        "trust_level": 2
      },
      {
        "id": 874,
        "username": "Golemboy",
        "name": null,
        "avatar_template": "/user_avatar/forum.magicball.net/golemboy/{size}/191_2.png",
        "post_count": 5,
        "primary_group_name": null,
        "flair_name": null,
        "flair_url": null,
        "flair_color": null,
        "flair_bg_color": null,
        "flair_group_id": null,
        "trust_level": 1
      },
      {
        "id": 1079,
        "username": "Kitarii",
        "name": null,
        "avatar_template": "/user_avatar/forum.magicball.net/kitarii/{size}/217_2.png",
        "post_count": 4,
        "primary_group_name": null,
        "flair_name": null,
        "flair_url": null,
        "flair_color": null,
        "flair_bg_color": null,
        "flair_group_id": null,
        "moderator": true,
        "trust_level": 1
      },
      {
        "id": 463,
        "username": "xesf",
        "name": null,
        "avatar_template": "/user_avatar/forum.magicball.net/xesf/{size}/122_2.png",
        "post_count": 3,
        "primary_group_name": null,
        "flair_name": null,
        "flair_url": null,
        "flair_color": null,
        "flair_bg_color": null,
        "flair_group_id": null,
        "trust_level": 2
      },
      {
        "id": 2,
        "username": "ChaosFish",
        "name": null,
        "avatar_template": "/user_avatar/forum.magicball.net/chaosfish/{size}/2_2.png",
        "post_count": 1,
        "primary_group_name": null,
        "flair_name": null,
        "flair_url": null,
        "flair_color": null,
        "flair_bg_color": null,
        "flair_group_id": null,
        "trust_level": 1
      }
    ],
    "created_by": {
      "id": 1285,
      "username": "Blafards61",
      "name": null,
      "avatar_template": "/user_avatar/forum.magicball.net/blafards61/{size}/32_2.png"
    },
    "last_poster": {
      "id": 463,
      "username": "xesf",
      "name": null,
      "avatar_template": "/user_avatar/forum.magicball.net/xesf/{size}/122_2.png"
    }
  },
  "pending_posts": [],
  "bookmarks": []
}